{"meta": {"total_reviews": 3716, "total_elite_reviews": 587, "total_regular_reviews": 3129, "business_count": 60, "city": "Ruskin", "state": "FL"}, "star_counts": {"1": {"elite": 34, "regular": 533, "total": 567, "elite_pct": 6.0}, "2": {"elite": 44, "regular": 288, "total": 332, "elite_pct": 13.3}, "3": {"elite": 126, "regular": 294, "total": 420, "elite_pct": 30.0}, "4": {"elite": 200, "regular": 595, "total": 795, "elite_pct": 25.2}, "5": {"elite": 183, "regular": 1419, "total": 1602, "elite_pct": 11.4}}, "trajectories": {"good": {"elite": {"1": {"avg": 3.733, "count": 15}, "3": {"avg": 4.048, "count": 14}, "5": {"avg": 4.0, "count": 13}, "10": {"avg": 4.0, "count": 7}, "25": {"avg": 4.0, "count": 3}}, "all": {"1": {"avg": 4.118, "count": 17}, "3": {"avg": 4.078, "count": 17}, "5": {"avg": 4.165, "count": 17}, "10": {"avg": 4.073, "count": 15}, "25": {"avg": 4.089, "count": 13}, "50": {"avg": 4.136, "count": 9}, "100": {"avg": 4.2, "count": 5}}, "regular": {"1": {"avg": 4.059, "count": 17}, "3": {"avg": 4.157, "count": 17}, "5": {"avg": 4.287, "count": 16}, "10": {"avg": 4.08, "count": 15}, "25": {"avg": 4.137, "count": 12}, "50": {"avg": 4.151, "count": 7}, "100": {"avg": 4.188, "count": 5}}}, "average": {"regular": {"1": {"avg": 3.8, "count": 10}, "3": {"avg": 3.867, "count": 10}, "5": {"avg": 3.78, "count": 10}, "10": {"avg": 3.67, "count": 10}, "25": {"avg": 3.496, "count": 5}, "50": {"avg": 3.31, "count": 2}, "100": {"avg": 2.9, "count": 1}}, "all": {"1": {"avg": 4.1, "count": 10}, "3": {"avg": 3.967, "count": 10}, "5": {"avg": 3.84, "count": 10}, "10": {"avg": 3.75, "count": 10}, "25": {"avg": 3.528, "count": 5}, "50": {"avg": 3.41, "count": 2}, "100": {"avg": 3.06, "count": 1}}, "elite": {"1": {"avg": 3.6, "count": 10}, "3": {"avg": 3.905, "count": 7}, "5": {"avg": 3.8, "count": 6}, "10": {"avg": 3.7, "count": 2}, "25": {"avg": 3.32, "count": 1}, "50": {"avg": 3.5, "count": 1}}}, "poor": {"regular": {"1": {"avg": 3.071, "count": 14}, "3": {"avg": 2.5, "count": 14}, "5": {"avg": 2.443, "count": 14}, "10": {"avg": 2.244, "count": 9}, "25": {"avg": 2.2, "count": 7}, "50": {"avg": 2.31, "count": 2}}, "all": {"1": {"avg": 3.357, "count": 14}, "3": {"avg": 2.762, "count": 14}, "5": {"avg": 2.686, "count": 14}, "10": {"avg": 2.436, "count": 11}, "25": {"avg": 2.38, "count": 8}, "50": {"avg": 2.74, "count": 2}}, "elite": {"1": {"avg": 2.769, "count": 13}, "3": {"avg": 3.259, "count": 9}, "5": {"avg": 3.033, "count": 6}, "10": {"avg": 3.2, "count": 2}}}, "strong": {"elite": {"1": {"avg": 4.1, "count": 10}, "3": {"avg": 4.556, "count": 6}, "5": {"avg": 4.55, "count": 4}, "10": {"avg": 4.4, "count": 3}, "25": {"avg": 4.32, "count": 2}}, "all": {"1": {"avg": 4.5, "count": 10}, "3": {"avg": 4.533, "count": 10}, "5": {"avg": 4.58, "count": 10}, "10": {"avg": 4.4, "count": 5}, "25": {"avg": 4.34, "count": 4}, "50": {"avg": 4.393, "count": 3}, "100": {"avg": 4.45, "count": 2}}, "regular": {"1": {"avg": 4.6, "count": 10}, "3": {"avg": 4.7, "count": 10}, "5": {"avg": 4.571, "count": 7}, "10": {"avg": 4.3, "count": 5}, "25": {"avg": 4.39, "count": 4}, "50": {"avg": 4.413, "count": 3}, "100": {"avg": 4.475, "count": 2}}}, "weak": {"regular": {"1": {"avg": 3.444, "count": 9}, "3": {"avg": 3.185, "count": 9}, "5": {"avg": 2.778, "count": 9}, "10": {"avg": 3.075, "count": 8}, "25": {"avg": 3.32, "count": 5}, "50": {"avg": 3.08, "count": 4}}, "all": {"1": {"avg": 3.222, "count": 9}, "3": {"avg": 3.111, "count": 9}, "5": {"avg": 2.978, "count": 9}, "10": {"avg": 2.95, "count": 8}, "25": {"avg": 3.16, "count": 7}, "50": {"avg": 3.145, "count": 4}}, "elite": {"1": {"avg": 3.111, "count": 9}, "3": {"avg": 3.074, "count": 9}, "5": {"avg": 3.35, "count": 8}, "10": {"avg": 3.467, "count": 3}}}}, "words": {"1": {"elite": [{"word": "cold", "count": 12, "sentiment": -0.6}, {"word": "ordered", "count": 9, "sentiment": 0.0}, {"word": "see", "count": 7, "sentiment": 0.0}, {"word": "found", "count": 6, "sentiment": 0.0}, {"word": "little", "count": 6, "sentiment": -0.188}, {"word": "hot", "count": 6, "sentiment": 0.25}, {"word": "served", "count": 5, "sentiment": 0.0}, {"word": "wrong", "count": 5, "sentiment": -0.5}, {"word": "pay", "count": 5, "sentiment": 0.0}, {"word": "gave", "count": 5, "sentiment": 0.0}, {"word": "better", "count": 5, "sentiment": 0.5}, {"word": "going", "count": 5, "sentiment": 0.0}, {"word": "coming", "count": 4, "sentiment": 0.0}, {"word": "fried", "count": 4, "sentiment": 0.0}, {"word": "old", "count": 4, "sentiment": 0.1}, {"word": "wearing", "count": 4, "sentiment": 0.0}, {"word": "getting", "count": 4, "sentiment": 0.0}, {"word": "small", "count": 4, "sentiment": -0.25}, {"word": "cooked", "count": 4, "sentiment": 0.0}, {"word": "stopped", "count": 4, "sentiment": 0.0}, {"word": "poor", "count": 4, "sentiment": -0.4}, {"word": "give", "count": 4, "sentiment": 0.0}, {"word": "closed", "count": 4, "sentiment": -0.1}, {"word": "decided", "count": 4, "sentiment": 0.0}, {"word": "hard", "count": 4, "sentiment": -0.292}, {"word": "many", "count": 4, "sentiment": 0.5}, {"word": "awful", "count": 4, "sentiment": -1.0}, {"word": "call", "count": 4, "sentiment": 0.0}, {"word": "thought", "count": 4, "sentiment": 0.0}, {"word": "fresh", "count": 3, "sentiment": 0.3}, {"word": "working", "count": 3, "sentiment": 0.0}, {"word": "based", "count": 3, "sentiment": 0.0}, {"word": "seasoned", "count": 3, "sentiment": 0.25}, {"word": "overall", "count": 3, "sentiment": 0.0}, {"word": "happy", "count": 3, "sentiment": 0.8}, {"word": "ask", "count": 3, "sentiment": 0.0}, {"word": "work", "count": 3, "sentiment": 0.0}, {"word": "dirty", "count": 3, "sentiment": -0.6}, {"word": "second", "count": 3, "sentiment": 0.0}, {"word": "prepared", "count": 3, "sentiment": 0.0}, {"word": "cheese", "count": 3, "sentiment": 0.0}, {"word": "return", "count": 3, "sentiment": 0.0}, {"word": "free", "count": 3, "sentiment": 0.4}, {"word": "returned", "count": 3, "sentiment": 0.0}, {"word": "enough", "count": 3, "sentiment": 0.0}, {"word": "tasted", "count": 3, "sentiment": 0.0}, {"word": "dry", "count": 3, "sentiment": -0.067}, {"word": "received", "count": 3, "sentiment": 0.0}, {"word": "called", "count": 3, "sentiment": 0.0}, {"word": "disappointed", "count": 3, "sentiment": -0.75}], "regular": [{"word": "ordered", "count": 196, "sentiment": 0.0}, {"word": "cold", "count": 103, "sentiment": -0.6}, {"word": "give", "count": 86, "sentiment": 0.0}, {"word": "eat", "count": 82, "sentiment": 0.0}, {"word": "going", "count": 82, "sentiment": 0.0}, {"word": "called", "count": 78, "sentiment": 0.0}, {"word": "horrible", "count": 71, "sentiment": -1.0}, {"word": "waiting", "count": 70, "sentiment": 0.0}, {"word": "worst", "count": 63, "sentiment": -1.0}, {"word": "left", "count": 62, "sentiment": 0.0}, {"word": "waited", "count": 58, "sentiment": 0.0}, {"word": "terrible", "count": 57, "sentiment": -1.0}, {"word": "old", "count": 57, "sentiment": 0.1}, {"word": "wrong", "count": 56, "sentiment": -0.5}, {"word": "see", "count": 52, "sentiment": 0.0}, {"word": "ask", "count": 51, "sentiment": 0.0}, {"word": "decided", "count": 48, "sentiment": 0.0}, {"word": "disappointed", "count": 48, "sentiment": -0.75}, {"word": "gave", "count": 46, "sentiment": 0.0}, {"word": "many", "count": 45, "sentiment": 0.5}, {"word": "hot", "count": 45, "sentiment": 0.25}, {"word": "better", "count": 45, "sentiment": 0.5}, {"word": "small", "count": 41, "sentiment": -0.25}, {"word": "sure", "count": 41, "sentiment": 0.5}, {"word": "put", "count": 40, "sentiment": 0.0}, {"word": "arrived", "count": 39, "sentiment": 0.0}, {"word": "nice", "count": 39, "sentiment": 0.6}, {"word": "walked", "count": 39, "sentiment": 0.0}, {"word": "little", "count": 39, "sentiment": -0.188}, {"word": "rude", "count": 39, "sentiment": -0.3}, {"word": "long", "count": 39, "sentiment": -0.05}, {"word": "tasted", "count": 38, "sentiment": 0.0}, {"word": "least", "count": 38, "sentiment": -0.3}, {"word": "served", "count": 38, "sentiment": 0.0}, {"word": "looked", "count": 38, "sentiment": 0.0}, {"word": "tell", "count": 37, "sentiment": 0.0}, {"word": "fried", "count": 37, "sentiment": 0.0}, {"word": "done", "count": 37, "sentiment": 0.0}, {"word": "cooked", "count": 37, "sentiment": 0.0}, {"word": "received", "count": 37, "sentiment": 0.0}, {"word": "slow", "count": 36, "sentiment": -0.3}, {"word": "find", "count": 36, "sentiment": 0.0}, {"word": "dry", "count": 35, "sentiment": -0.067}, {"word": "sitting", "count": 35, "sentiment": 0.0}, {"word": "brought", "count": 35, "sentiment": 0.0}, {"word": "second", "count": 35, "sentiment": 0.0}, {"word": "big", "count": 34, "sentiment": 0.0}, {"word": "wait", "count": 33, "sentiment": 0.0}, {"word": "busy", "count": 33, "sentiment": 0.1}, {"word": "saw", "count": 33, "sentiment": 0.0}]}, "2": {"elite": [{"word": "ordered", "count": 14, "sentiment": 0.0}, {"word": "nice", "count": 12, "sentiment": 0.6}, {"word": "see", "count": 11, "sentiment": 0.0}, {"word": "fresh", "count": 10, "sentiment": 0.3}, {"word": "ask", "count": 9, "sentiment": 0.0}, {"word": "give", "count": 8, "sentiment": 0.0}, {"word": "hot", "count": 8, "sentiment": 0.25}, {"word": "many", "count": 8, "sentiment": 0.5}, {"word": "eat", "count": 7, "sentiment": 0.0}, {"word": "seemed", "count": 7, "sentiment": 0.0}, {"word": "overall", "count": 7, "sentiment": 0.0}, {"word": "friendly", "count": 7, "sentiment": 0.375}, {"word": "cheese", "count": 7, "sentiment": 0.0}, {"word": "call", "count": 7, "sentiment": 0.0}, {"word": "wait", "count": 7, "sentiment": 0.0}, {"word": "waited", "count": 7, "sentiment": 0.0}, {"word": "dry", "count": 6, "sentiment": -0.067}, {"word": "decent", "count": 6, "sentiment": 0.167}, {"word": "small", "count": 6, "sentiment": -0.25}, {"word": "little", "count": 6, "sentiment": -0.188}, {"word": "better", "count": 6, "sentiment": 0.5}, {"word": "average", "count": 6, "sentiment": -0.15}, {"word": "hard", "count": 6, "sentiment": -0.292}, {"word": "done", "count": 6, "sentiment": 0.0}, {"word": "tasted", "count": 5, "sentiment": 0.0}, {"word": "trying", "count": 5, "sentiment": 0.0}, {"word": "disappointing", "count": 5, "sentiment": -0.6}, {"word": "busy", "count": 5, "sentiment": 0.1}, {"word": "warm", "count": 5, "sentiment": 0.6}, {"word": "cold", "count": 5, "sentiment": -0.6}, {"word": "find", "count": 5, "sentiment": 0.0}, {"word": "eating", "count": 5, "sentiment": 0.0}, {"word": "considering", "count": 5, "sentiment": 0.0}, {"word": "similar", "count": 4, "sentiment": 0.0}, {"word": "eaten", "count": 4, "sentiment": 0.0}, {"word": "enough", "count": 4, "sentiment": 0.0}, {"word": "slow", "count": 4, "sentiment": -0.3}, {"word": "red", "count": 4, "sentiment": 0.0}, {"word": "given", "count": 4, "sentiment": 0.0}, {"word": "taken", "count": 4, "sentiment": 0.0}, {"word": "dirty", "count": 4, "sentiment": -0.6}, {"word": "disappointed", "count": 4, "sentiment": -0.75}, {"word": "right", "count": 4, "sentiment": 0.286}, {"word": "chicken", "count": 4, "sentiment": -0.6}, {"word": "noodle", "count": 4, "sentiment": 0.0}, {"word": "full", "count": 4, "sentiment": 0.35}, {"word": "seem", "count": 4, "sentiment": 0.0}, {"word": "outside", "count": 4, "sentiment": 0.0}, {"word": "forgot", "count": 4, "sentiment": 0.0}, {"word": "left", "count": 4, "sentiment": 0.0}], "regular": [{"word": "ordered", "count": 115, "sentiment": 0.0}, {"word": "little", "count": 39, "sentiment": -0.188}, {"word": "nice", "count": 39, "sentiment": 0.6}, {"word": "better", "count": 35, "sentiment": 0.5}, {"word": "many", "count": 35, "sentiment": 0.5}, {"word": "give", "count": 34, "sentiment": 0.0}, {"word": "cooked", "count": 32, "sentiment": 0.0}, {"word": "disappointed", "count": 30, "sentiment": -0.75}, {"word": "eat", "count": 29, "sentiment": 0.0}, {"word": "sure", "count": 29, "sentiment": 0.5}, {"word": "going", "count": 28, "sentiment": 0.0}, {"word": "cold", "count": 28, "sentiment": -0.6}, {"word": "hot", "count": 27, "sentiment": 0.25}, {"word": "decided", "count": 24, "sentiment": 0.0}, {"word": "old", "count": 24, "sentiment": 0.1}, {"word": "long", "count": 24, "sentiment": -0.05}, {"word": "left", "count": 23, "sentiment": 0.0}, {"word": "brought", "count": 22, "sentiment": 0.0}, {"word": "fish", "count": 22, "sentiment": 0.0}, {"word": "looking", "count": 21, "sentiment": 0.0}, {"word": "slow", "count": 21, "sentiment": -0.3}, {"word": "dry", "count": 20, "sentiment": -0.067}, {"word": "ask", "count": 19, "sentiment": 0.0}, {"word": "special", "count": 19, "sentiment": 0.357}, {"word": "terrible", "count": 18, "sentiment": -1.0}, {"word": "tasted", "count": 18, "sentiment": 0.0}, {"word": "small", "count": 18, "sentiment": -0.25}, {"word": "busy", "count": 18, "sentiment": 0.1}, {"word": "fried", "count": 18, "sentiment": 0.0}, {"word": "waited", "count": 17, "sentiment": 0.0}, {"word": "large", "count": 17, "sentiment": 0.214}, {"word": "paid", "count": 16, "sentiment": 0.0}, {"word": "arrived", "count": 16, "sentiment": 0.0}, {"word": "used", "count": 16, "sentiment": 0.0}, {"word": "several", "count": 16, "sentiment": 0.0}, {"word": "average", "count": 16, "sentiment": -0.15}, {"word": "see", "count": 16, "sentiment": 0.0}, {"word": "served", "count": 16, "sentiment": 0.0}, {"word": "done", "count": 15, "sentiment": 0.0}, {"word": "wait", "count": 15, "sentiment": 0.0}, {"word": "getting", "count": 15, "sentiment": 0.0}, {"word": "cheese", "count": 15, "sentiment": 0.0}, {"word": "seems", "count": 15, "sentiment": 0.0}, {"word": "pay", "count": 14, "sentiment": 0.0}, {"word": "ate", "count": 14, "sentiment": 0.0}, {"word": "seated", "count": 14, "sentiment": 0.0}, {"word": "find", "count": 14, "sentiment": 0.0}, {"word": "disappointing", "count": 14, "sentiment": -0.6}, {"word": "salad", "count": 14, "sentiment": 0.0}, {"word": "expect", "count": 14, "sentiment": 0.0}]}, "3": {"elite": [{"word": "ordered", "count": 59, "sentiment": 0.0}, {"word": "nice", "count": 49, "sentiment": 0.6}, {"word": "hot", "count": 35, "sentiment": 0.25}, {"word": "give", "count": 30, "sentiment": 0.0}, {"word": "small", "count": 27, "sentiment": -0.25}, {"word": "little", "count": 24, "sentiment": -0.188}, {"word": "many", "count": 23, "sentiment": 0.5}, {"word": "fried", "count": 21, "sentiment": 0.0}, {"word": "see", "count": 20, "sentiment": 0.0}, {"word": "eat", "count": 20, "sentiment": 0.0}, {"word": "friendly", "count": 19, "sentiment": 0.375}, {"word": "overall", "count": 19, "sentiment": 0.0}, {"word": "fresh", "count": 19, "sentiment": 0.3}, {"word": "tasted", "count": 18, "sentiment": 0.0}, {"word": "better", "count": 17, "sentiment": 0.5}, {"word": "clean", "count": 17, "sentiment": 0.367}, {"word": "large", "count": 17, "sentiment": 0.214}, {"word": "fish", "count": 17, "sentiment": 0.0}, {"word": "love", "count": 16, "sentiment": 0.5}, {"word": "find", "count": 16, "sentiment": 0.0}, {"word": "sure", "count": 16, "sentiment": 0.5}, {"word": "going", "count": 15, "sentiment": 0.0}, {"word": "average", "count": 15, "sentiment": -0.15}, {"word": "local", "count": 14, "sentiment": 0.0}, {"word": "delicious", "count": 14, "sentiment": 1.0}, {"word": "busy", "count": 13, "sentiment": 0.1}, {"word": "seem", "count": 13, "sentiment": 0.0}, {"word": "outside", "count": 12, "sentiment": 0.0}, {"word": "cooked", "count": 12, "sentiment": 0.0}, {"word": "use", "count": 12, "sentiment": 0.0}, {"word": "big", "count": 12, "sentiment": 0.0}, {"word": "ready", "count": 12, "sentiment": 0.2}, {"word": "decent", "count": 12, "sentiment": 0.167}, {"word": "soft", "count": 11, "sentiment": 0.1}, {"word": "disappointed", "count": 11, "sentiment": -0.75}, {"word": "sit", "count": 11, "sentiment": 0.0}, {"word": "found", "count": 11, "sentiment": 0.0}, {"word": "check", "count": 11, "sentiment": 0.0}, {"word": "super", "count": 11, "sentiment": 0.333}, {"word": "slow", "count": 11, "sentiment": -0.3}, {"word": "served", "count": 11, "sentiment": 0.0}, {"word": "enjoyed", "count": 10, "sentiment": 0.5}, {"word": "different", "count": 10, "sentiment": 0.0}, {"word": "thought", "count": 10, "sentiment": 0.0}, {"word": "wait", "count": 10, "sentiment": 0.0}, {"word": "expect", "count": 10, "sentiment": 0.0}, {"word": "eating", "count": 10, "sentiment": 0.0}, {"word": "seating", "count": 10, "sentiment": 0.0}, {"word": "tasty", "count": 10, "sentiment": 0.0}, {"word": "cheese", "count": 10, "sentiment": 0.0}], "regular": [{"word": "little", "count": 61, "sentiment": -0.188}, {"word": "ordered", "count": 58, "sentiment": 0.0}, {"word": "nice", "count": 56, "sentiment": 0.6}, {"word": "small", "count": 37, "sentiment": -0.25}, {"word": "better", "count": 33, "sentiment": 0.5}, {"word": "give", "count": 32, "sentiment": 0.0}, {"word": "delicious", "count": 29, "sentiment": 1.0}, {"word": "fish", "count": 24, "sentiment": 0.0}, {"word": "friendly", "count": 23, "sentiment": 0.375}, {"word": "fresh", "count": 23, "sentiment": 0.3}, {"word": "hot", "count": 23, "sentiment": 0.25}, {"word": "sure", "count": 23, "sentiment": 0.5}, {"word": "left", "count": 22, "sentiment": 0.0}, {"word": "old", "count": 22, "sentiment": 0.1}, {"word": "clean", "count": 21, "sentiment": 0.367}, {"word": "cold", "count": 21, "sentiment": -0.6}, {"word": "eat", "count": 21, "sentiment": 0.0}, {"word": "dry", "count": 21, "sentiment": -0.067}, {"word": "overall", "count": 20, "sentiment": 0.0}, {"word": "german", "count": 20, "sentiment": 0.0}, {"word": "disappointed", "count": 19, "sentiment": -0.75}, {"word": "wait", "count": 19, "sentiment": 0.0}, {"word": "looked", "count": 19, "sentiment": 0.0}, {"word": "slow", "count": 19, "sentiment": -0.3}, {"word": "love", "count": 18, "sentiment": 0.5}, {"word": "fried", "count": 18, "sentiment": 0.0}, {"word": "put", "count": 18, "sentiment": 0.0}, {"word": "tasty", "count": 17, "sentiment": 0.0}, {"word": "decent", "count": 17, "sentiment": 0.167}, {"word": "thought", "count": 17, "sentiment": 0.0}, {"word": "average", "count": 17, "sentiment": -0.15}, {"word": "live", "count": 17, "sentiment": 0.136}, {"word": "seemed", "count": 16, "sentiment": 0.0}, {"word": "cheese", "count": 16, "sentiment": 0.0}, {"word": "many", "count": 16, "sentiment": 0.5}, {"word": "tasted", "count": 15, "sentiment": 0.0}, {"word": "extra", "count": 15, "sentiment": 0.0}, {"word": "different", "count": 15, "sentiment": 0.0}, {"word": "sit", "count": 15, "sentiment": 0.0}, {"word": "greek", "count": 14, "sentiment": 0.0}, {"word": "bring", "count": 14, "sentiment": 0.0}, {"word": "long", "count": 14, "sentiment": -0.05}, {"word": "looking", "count": 14, "sentiment": 0.0}, {"word": "seated", "count": 14, "sentiment": 0.0}, {"word": "cooked", "count": 13, "sentiment": 0.0}, {"word": "outside", "count": 13, "sentiment": 0.0}, {"word": "waited", "count": 13, "sentiment": 0.0}, {"word": "local", "count": 12, "sentiment": 0.0}, {"word": "mediocre", "count": 12, "sentiment": -0.5}, {"word": "gave", "count": 12, "sentiment": 0.0}]}, "4": {"elite": [{"word": "nice", "count": 68, "sentiment": 0.6}, {"word": "little", "count": 67, "sentiment": -0.188}, {"word": "ordered", "count": 51, "sentiment": 0.0}, {"word": "fresh", "count": 50, "sentiment": 0.3}, {"word": "delicious", "count": 43, "sentiment": 1.0}, {"word": "hot", "count": 38, "sentiment": 0.25}, {"word": "german", "count": 35, "sentiment": 0.0}, {"word": "small", "count": 34, "sentiment": -0.25}, {"word": "busy", "count": 33, "sentiment": 0.1}, {"word": "friendly", "count": 31, "sentiment": 0.375}, {"word": "clean", "count": 30, "sentiment": 0.367}, {"word": "eat", "count": 28, "sentiment": 0.0}, {"word": "excellent", "count": 24, "sentiment": 1.0}, {"word": "fried", "count": 24, "sentiment": 0.0}, {"word": "tasty", "count": 23, "sentiment": 0.0}, {"word": "mexican", "count": 23, "sentiment": 0.0}, {"word": "many", "count": 21, "sentiment": 0.5}, {"word": "sure", "count": 21, "sentiment": 0.5}, {"word": "cheese", "count": 21, "sentiment": 0.0}, {"word": "see", "count": 21, "sentiment": 0.0}, {"word": "large", "count": 20, "sentiment": 0.214}, {"word": "going", "count": 19, "sentiment": 0.0}, {"word": "served", "count": 19, "sentiment": 0.0}, {"word": "big", "count": 19, "sentiment": 0.0}, {"word": "recommend", "count": 19, "sentiment": 0.0}, {"word": "find", "count": 19, "sentiment": 0.0}, {"word": "found", "count": 18, "sentiment": 0.0}, {"word": "sweet", "count": 18, "sentiment": 0.35}, {"word": "give", "count": 18, "sentiment": 0.0}, {"word": "happy", "count": 18, "sentiment": 0.8}, {"word": "open", "count": 18, "sentiment": 0.0}, {"word": "live", "count": 18, "sentiment": 0.136}, {"word": "old", "count": 18, "sentiment": 0.1}, {"word": "favorite", "count": 17, "sentiment": 0.5}, {"word": "authentic", "count": 17, "sentiment": 0.5}, {"word": "enjoyed", "count": 17, "sentiment": 0.5}, {"word": "ruskin", "count": 17, "sentiment": 0.0}, {"word": "special", "count": 16, "sentiment": 0.357}, {"word": "full", "count": 16, "sentiment": 0.35}, {"word": "loved", "count": 16, "sentiment": 0.7}, {"word": "perfect", "count": 16, "sentiment": 1.0}, {"word": "love", "count": 16, "sentiment": 0.5}, {"word": "enjoy", "count": 16, "sentiment": 0.4}, {"word": "different", "count": 16, "sentiment": 0.0}, {"word": "quick", "count": 16, "sentiment": 0.333}, {"word": "decided", "count": 16, "sentiment": 0.0}, {"word": "right", "count": 16, "sentiment": 0.286}, {"word": "reasonable", "count": 15, "sentiment": 0.2}, {"word": "amazing", "count": 15, "sentiment": 0.6}, {"word": "looking", "count": 15, "sentiment": 0.0}], "regular": [{"word": "little", "count": 114, "sentiment": -0.188}, {"word": "nice", "count": 100, "sentiment": 0.6}, {"word": "delicious", "count": 95, "sentiment": 1.0}, {"word": "ordered", "count": 89, "sentiment": 0.0}, {"word": "friendly", "count": 78, "sentiment": 0.375}, {"word": "fresh", "count": 66, "sentiment": 0.3}, {"word": "excellent", "count": 65, "sentiment": 1.0}, {"word": "hot", "count": 62, "sentiment": 0.25}, {"word": "eat", "count": 55, "sentiment": 0.0}, {"word": "tasty", "count": 53, "sentiment": 0.0}, {"word": "enjoyed", "count": 49, "sentiment": 0.5}, {"word": "fish", "count": 45, "sentiment": 0.0}, {"word": "small", "count": 44, "sentiment": -0.25}, {"word": "love", "count": 42, "sentiment": 0.5}, {"word": "amazing", "count": 42, "sentiment": 0.6}, {"word": "large", "count": 41, "sentiment": 0.214}, {"word": "clean", "count": 39, "sentiment": 0.367}, {"word": "fried", "count": 38, "sentiment": 0.0}, {"word": "find", "count": 37, "sentiment": 0.0}, {"word": "recommend", "count": 36, "sentiment": 0.0}, {"word": "going", "count": 36, "sentiment": 0.0}, {"word": "wait", "count": 35, "sentiment": 0.0}, {"word": "live", "count": 34, "sentiment": 0.136}, {"word": "busy", "count": 33, "sentiment": 0.1}, {"word": "give", "count": 33, "sentiment": 0.0}, {"word": "german", "count": 33, "sentiment": 0.0}, {"word": "cheese", "count": 32, "sentiment": 0.0}, {"word": "sure", "count": 32, "sentiment": 0.5}, {"word": "old", "count": 31, "sentiment": 0.1}, {"word": "better", "count": 30, "sentiment": 0.5}, {"word": "authentic", "count": 30, "sentiment": 0.5}, {"word": "many", "count": 29, "sentiment": 0.5}, {"word": "outside", "count": 29, "sentiment": 0.0}, {"word": "awesome", "count": 28, "sentiment": 1.0}, {"word": "served", "count": 27, "sentiment": 0.0}, {"word": "cooked", "count": 27, "sentiment": 0.0}, {"word": "different", "count": 27, "sentiment": 0.0}, {"word": "see", "count": 27, "sentiment": 0.0}, {"word": "perfect", "count": 26, "sentiment": 1.0}, {"word": "big", "count": 26, "sentiment": 0.0}, {"word": "done", "count": 26, "sentiment": 0.0}, {"word": "mexican", "count": 26, "sentiment": 0.0}, {"word": "quick", "count": 25, "sentiment": 0.333}, {"word": "special", "count": 25, "sentiment": 0.357}, {"word": "huge", "count": 24, "sentiment": 0.4}, {"word": "full", "count": 24, "sentiment": 0.35}, {"word": "wonderful", "count": 24, "sentiment": 1.0}, {"word": "decent", "count": 24, "sentiment": 0.167}, {"word": "loved", "count": 24, "sentiment": 0.7}, {"word": "attentive", "count": 24, "sentiment": 0.4}]}, "5": {"elite": [{"word": "delicious", "count": 64, "sentiment": 1.0}, {"word": "fresh", "count": 54, "sentiment": 0.3}, {"word": "ordered", "count": 32, "sentiment": 0.0}, {"word": "amazing", "count": 32, "sentiment": 0.6}, {"word": "love", "count": 31, "sentiment": 0.5}, {"word": "hot", "count": 30, "sentiment": 0.25}, {"word": "german", "count": 30, "sentiment": 0.0}, {"word": "little", "count": 27, "sentiment": -0.188}, {"word": "friendly", "count": 26, "sentiment": 0.375}, {"word": "authentic", "count": 25, "sentiment": 0.5}, {"word": "eat", "count": 23, "sentiment": 0.0}, {"word": "many", "count": 22, "sentiment": 0.5}, {"word": "nice", "count": 22, "sentiment": 0.6}, {"word": "fried", "count": 21, "sentiment": 0.0}, {"word": "loved", "count": 19, "sentiment": 0.7}, {"word": "happy", "count": 19, "sentiment": 0.8}, {"word": "find", "count": 19, "sentiment": 0.0}, {"word": "awesome", "count": 18, "sentiment": 1.0}, {"word": "large", "count": 18, "sentiment": 0.214}, {"word": "big", "count": 18, "sentiment": 0.0}, {"word": "full", "count": 17, "sentiment": 0.35}, {"word": "free", "count": 17, "sentiment": 0.4}, {"word": "excellent", "count": 17, "sentiment": 1.0}, {"word": "sure", "count": 17, "sentiment": 0.5}, {"word": "fish", "count": 17, "sentiment": 0.0}, {"word": "sweet", "count": 17, "sentiment": 0.35}, {"word": "small", "count": 17, "sentiment": -0.25}, {"word": "favorite", "count": 17, "sentiment": 0.5}, {"word": "cooked", "count": 16, "sentiment": 0.0}, {"word": "fantastic", "count": 16, "sentiment": 0.4}, {"word": "huge", "count": 16, "sentiment": 0.4}, {"word": "cheese", "count": 16, "sentiment": 0.0}, {"word": "tasty", "count": 15, "sentiment": 0.0}, {"word": "mexican", "count": 15, "sentiment": 0.0}, {"word": "wonderful", "count": 14, "sentiment": 1.0}, {"word": "perfect", "count": 14, "sentiment": 1.0}, {"word": "gluten", "count": 14, "sentiment": 0.0}, {"word": "found", "count": 14, "sentiment": 0.0}, {"word": "different", "count": 14, "sentiment": 0.0}, {"word": "stop", "count": 14, "sentiment": 0.0}, {"word": "recommend", "count": 14, "sentiment": 0.0}, {"word": "busy", "count": 14, "sentiment": 0.1}, {"word": "pick", "count": 14, "sentiment": 0.0}, {"word": "super", "count": 13, "sentiment": 0.333}, {"word": "old", "count": 13, "sentiment": 0.1}, {"word": "comes", "count": 13, "sentiment": 0.0}, {"word": "stopped", "count": 13, "sentiment": 0.0}, {"word": "going", "count": 13, "sentiment": 0.0}, {"word": "local", "count": 13, "sentiment": 0.0}, {"word": "special", "count": 13, "sentiment": 0.357}], "regular": [{"word": "delicious", "count": 331, "sentiment": 1.0}, {"word": "amazing", "count": 247, "sentiment": 0.6}, {"word": "fresh", "count": 208, "sentiment": 0.3}, {"word": "friendly", "count": 206, "sentiment": 0.375}, {"word": "love", "count": 193, "sentiment": 0.5}, {"word": "nice", "count": 178, "sentiment": 0.6}, {"word": "excellent", "count": 178, "sentiment": 1.0}, {"word": "little", "count": 157, "sentiment": -0.188}, {"word": "authentic", "count": 152, "sentiment": 0.5}, {"word": "recommend", "count": 146, "sentiment": 0.0}, {"word": "mexican", "count": 142, "sentiment": 0.0}, {"word": "hot", "count": 120, "sentiment": 0.25}, {"word": "awesome", "count": 119, "sentiment": 1.0}, {"word": "german", "count": 116, "sentiment": 0.0}, {"word": "eat", "count": 114, "sentiment": 0.0}, {"word": "ordered", "count": 112, "sentiment": 0.0}, {"word": "fried", "count": 94, "sentiment": 0.0}, {"word": "favorite", "count": 88, "sentiment": 0.5}, {"word": "loved", "count": 85, "sentiment": 0.7}, {"word": "clean", "count": 84, "sentiment": 0.367}, {"word": "wonderful", "count": 82, "sentiment": 1.0}, {"word": "fantastic", "count": 82, "sentiment": 0.4}, {"word": "found", "count": 81, "sentiment": 0.0}, {"word": "going", "count": 77, "sentiment": 0.0}, {"word": "fish", "count": 70, "sentiment": 0.0}, {"word": "stopped", "count": 69, "sentiment": 0.0}, {"word": "super", "count": 67, "sentiment": 0.333}, {"word": "enjoyed", "count": 67, "sentiment": 0.5}, {"word": "tasty", "count": 66, "sentiment": 0.0}, {"word": "big", "count": 66, "sentiment": 0.0}, {"word": "sure", "count": 63, "sentiment": 0.5}, {"word": "disappointed", "count": 63, "sentiment": -0.75}, {"word": "perfect", "count": 63, "sentiment": 1.0}, {"word": "small", "count": 61, "sentiment": -0.25}, {"word": "large", "count": 60, "sentiment": 0.214}, {"word": "give", "count": 59, "sentiment": 0.0}, {"word": "looking", "count": 59, "sentiment": 0.0}, {"word": "reasonable", "count": 59, "sentiment": 0.2}, {"word": "live", "count": 56, "sentiment": 0.136}, {"word": "old", "count": 56, "sentiment": 0.1}, {"word": "happy", "count": 55, "sentiment": 0.8}, {"word": "cooked", "count": 53, "sentiment": 0.0}, {"word": "coming", "count": 50, "sentiment": 0.0}, {"word": "many", "count": 50, "sentiment": 0.5}, {"word": "special", "count": 49, "sentiment": 0.357}, {"word": "local", "count": 48, "sentiment": 0.0}, {"word": "find", "count": 48, "sentiment": 0.0}, {"word": "ruskin", "count": 47, "sentiment": 0.0}, {"word": "better", "count": 47, "sentiment": 0.5}, {"word": "enjoy", "count": 47, "sentiment": 0.4}]}}}