{"meta": {"total_reviews": 4947662, "total_elite_reviews": 1349549, "total_regular_reviews": 3598113, "business_count": 60736, "label": "United States"}, "star_counts": {"1": {"elite": 44985, "regular": 543218, "total": 588203, "elite_pct": 7.6}, "2": {"elite": 90466, "regular": 321021, "total": 411487, "elite_pct": 22.0}, "3": {"elite": 228837, "regular": 332725, "total": 561562, "elite_pct": 40.8}, "4": {"elite": 491494, "regular": 691181, "total": 1182675, "elite_pct": 41.6}, "5": {"elite": 493767, "regular": 1709968, "total": 2203735, "elite_pct": 22.4}}, "trajectories": {"weak": {"regular": {"1": {"avg": 3.282, "count": 8489}, "3": {"avg": 3.169, "count": 8284}, "5": {"avg": 3.123, "count": 7606}, "10": {"avg": 3.074, "count": 5890}, "25": {"avg": 3.038, "count": 3494}, "50": {"avg": 3.022, "count": 1886}, "100": {"avg": 3.02, "count": 786}}, "all": {"1": {"avg": 3.496, "count": 8502}, "3": {"avg": 3.348, "count": 8502}, "5": {"avg": 3.265, "count": 8502}, "10": {"avg": 3.209, "count": 6724}, "25": {"avg": 3.148, "count": 4281}, "50": {"avg": 3.126, "count": 2471}, "100": {"avg": 3.106, "count": 1163}}, "elite": {"1": {"avg": 3.5, "count": 8114}, "3": {"avg": 3.408, "count": 6470}, "5": {"avg": 3.383, "count": 5039}, "10": {"avg": 3.359, "count": 3085}, "25": {"avg": 3.355, "count": 1194}, "50": {"avg": 3.348, "count": 416}, "100": {"avg": 3.319, "count": 103}}}, "average": {"elite": {"1": {"avg": 3.755, "count": 12568}, "3": {"avg": 3.703, "count": 10848}, "5": {"avg": 3.684, "count": 9076}, "10": {"avg": 3.674, "count": 6404}, "25": {"avg": 3.669, "count": 3219}, "50": {"avg": 3.666, "count": 1470}, "100": {"avg": 3.686, "count": 499}}, "all": {"1": {"avg": 3.846, "count": 12985}, "3": {"avg": 3.754, "count": 12985}, "5": {"avg": 3.701, "count": 12985}, "10": {"avg": 3.651, "count": 10999}, "25": {"avg": 3.595, "count": 7895}, "50": {"avg": 3.571, "count": 5319}, "100": {"avg": 3.56, "count": 3018}}, "regular": {"1": {"avg": 3.764, "count": 12976}, "3": {"avg": 3.676, "count": 12736}, "5": {"avg": 3.637, "count": 11935}, "10": {"avg": 3.592, "count": 9837}, "25": {"avg": 3.546, "count": 6645}, "50": {"avg": 3.526, "count": 4256}, "100": {"avg": 3.514, "count": 2215}}}, "good": {"regular": {"1": {"avg": 4.206, "count": 15184}, "3": {"avg": 4.152, "count": 14878}, "5": {"avg": 4.118, "count": 14004}, "10": {"avg": 4.078, "count": 11879}, "25": {"avg": 4.03, "count": 8735}, "50": {"avg": 4.004, "count": 6201}, "100": {"avg": 3.994, "count": 3769}}, "all": {"1": {"avg": 4.199, "count": 15202}, "3": {"avg": 4.157, "count": 15202}, "5": {"avg": 4.121, "count": 15202}, "10": {"avg": 4.082, "count": 13090}, "25": {"avg": 4.036, "count": 10033}, "50": {"avg": 4.011, "count": 7436}, "100": {"avg": 4.0, "count": 4891}}, "elite": {"1": {"avg": 4.049, "count": 14764}, "3": {"avg": 4.023, "count": 12971}, "5": {"avg": 4.011, "count": 11252}, "10": {"avg": 4.002, "count": 8633}, "25": {"avg": 4.004, "count": 5084}, "50": {"avg": 4.018, "count": 2875}, "100": {"avg": 4.037, "count": 1251}}}, "strong": {"regular": {"1": {"avg": 4.657, "count": 13302}, "3": {"avg": 4.646, "count": 12948}, "5": {"avg": 4.63, "count": 11922}, "10": {"avg": 4.59, "count": 9187}, "25": {"avg": 4.545, "count": 6093}, "50": {"avg": 4.508, "count": 3992}, "100": {"avg": 4.475, "count": 2146}}, "all": {"1": {"avg": 4.611, "count": 13338}, "3": {"avg": 4.61, "count": 13338}, "5": {"avg": 4.607, "count": 13338}, "10": {"avg": 4.572, "count": 10668}, "25": {"avg": 4.528, "count": 7242}, "50": {"avg": 4.491, "count": 5009}, "100": {"avg": 4.462, "count": 2941}}, "elite": {"1": {"avg": 4.471, "count": 12822}, "3": {"avg": 4.451, "count": 10533}, "5": {"avg": 4.435, "count": 8604}, "10": {"avg": 4.411, "count": 5980}, "25": {"avg": 4.397, "count": 3194}, "50": {"avg": 4.392, "count": 1640}, "100": {"avg": 4.393, "count": 693}}}, "poor": {"regular": {"1": {"avg": 2.514, "count": 10702}, "3": {"avg": 2.349, "count": 10560}, "5": {"avg": 2.275, "count": 9760}, "10": {"avg": 2.242, "count": 6877}, "25": {"avg": 2.238, "count": 3153}, "50": {"avg": 2.282, "count": 1253}, "100": {"avg": 2.321, "count": 346}}, "all": {"1": {"avg": 2.828, "count": 10709}, "3": {"avg": 2.604, "count": 10709}, "5": {"avg": 2.489, "count": 10709}, "10": {"avg": 2.435, "count": 7951}, "25": {"avg": 2.412, "count": 3901}, "50": {"avg": 2.443, "count": 1708}, "100": {"avg": 2.467, "count": 553}}, "elite": {"1": {"avg": 2.975, "count": 9580}, "3": {"avg": 2.935, "count": 6385}, "5": {"avg": 2.93, "count": 4251}, "10": {"avg": 2.946, "count": 1978}, "25": {"avg": 2.936, "count": 477}, "50": {"avg": 2.905, "count": 135}, "100": {"avg": 2.947, "count": 22}}}}, "words": {"1": {"elite": [{"word": "ordered", "count": 18422, "sentiment": 0.0}, {"word": "going", "count": 9028, "sentiment": 0.0}, {"word": "give", "count": 7778, "sentiment": 0.0}, {"word": "left", "count": 7166, "sentiment": 0.0}, {"word": "eat", "count": 7133, "sentiment": 0.0}, {"word": "see", "count": 6446, "sentiment": 0.0}, {"word": "waiting", "count": 5808, "sentiment": 0.0}, {"word": "better", "count": 5789, "sentiment": 0.5}, {"word": "sure", "count": 5649, "sentiment": 0.5}, {"word": "waited", "count": 5615, "sentiment": 0.0}, {"word": "worst", "count": 5421, "sentiment": -1.0}, {"word": "tasted", "count": 5414, "sentiment": 0.0}, {"word": "walked", "count": 5405, "sentiment": 0.0}, {"word": "looked", "count": 5321, "sentiment": 0.0}, {"word": "many", "count": 5027, "sentiment": 0.5}, {"word": "nice", "count": 5006, "sentiment": 0.6}, {"word": "decided", "count": 4981, "sentiment": 0.0}, {"word": "little", "count": 4940, "sentiment": -0.188}, {"word": "terrible", "count": 4783, "sentiment": -1.0}, {"word": "put", "count": 4697, "sentiment": 0.0}, {"word": "cold", "count": 4679, "sentiment": -0.6}, {"word": "ask", "count": 4667, "sentiment": 0.0}, {"word": "wait", "count": 4572, "sentiment": 0.0}, {"word": "called", "count": 4409, "sentiment": 0.0}, {"word": "disappointed", "count": 4366, "sentiment": -0.75}, {"word": "small", "count": 4362, "sentiment": -0.25}, {"word": "least", "count": 4281, "sentiment": -0.3}, {"word": "find", "count": 4146, "sentiment": 0.0}, {"word": "long", "count": 4026, "sentiment": -0.05}, {"word": "open", "count": 4017, "sentiment": 0.0}, {"word": "hot", "count": 4013, "sentiment": 0.25}, {"word": "wrong", "count": 4008, "sentiment": -0.5}, {"word": "horrible", "count": 3883, "sentiment": -1.0}, {"word": "seated", "count": 3870, "sentiment": 0.0}, {"word": "tell", "count": 3860, "sentiment": 0.0}, {"word": "sat", "count": 3856, "sentiment": 0.0}, {"word": "arrived", "count": 3849, "sentiment": 0.0}, {"word": "gave", "count": 3833, "sentiment": 0.0}, {"word": "thought", "count": 3767, "sentiment": 0.0}, {"word": "eating", "count": 3661, "sentiment": 0.0}, {"word": "old", "count": 3624, "sentiment": 0.1}, {"word": "brought", "count": 3553, "sentiment": 0.0}, {"word": "looking", "count": 3543, "sentiment": 0.0}, {"word": "busy", "count": 3528, "sentiment": 0.1}, {"word": "fried", "count": 3503, "sentiment": 0.0}, {"word": "getting", "count": 3490, "sentiment": 0.0}, {"word": "coming", "count": 3457, "sentiment": 0.0}, {"word": "used", "count": 3455, "sentiment": 0.0}, {"word": "served", "count": 3376, "sentiment": 0.0}, {"word": "leave", "count": 3354, "sentiment": 0.0}], "regular": [{"word": "ordered", "count": 170907, "sentiment": 0.0}, {"word": "going", "count": 81177, "sentiment": 0.0}, {"word": "give", "count": 73596, "sentiment": 0.0}, {"word": "worst", "count": 68018, "sentiment": -1.0}, {"word": "left", "count": 64710, "sentiment": 0.0}, {"word": "eat", "count": 62693, "sentiment": 0.0}, {"word": "called", "count": 60482, "sentiment": 0.0}, {"word": "waited", "count": 59124, "sentiment": 0.0}, {"word": "horrible", "count": 58633, "sentiment": -1.0}, {"word": "terrible", "count": 57104, "sentiment": -1.0}, {"word": "rude", "count": 55628, "sentiment": -0.3}, {"word": "waiting", "count": 53894, "sentiment": 0.0}, {"word": "cold", "count": 50938, "sentiment": -0.6}, {"word": "see", "count": 47049, "sentiment": 0.0}, {"word": "better", "count": 46334, "sentiment": 0.5}, {"word": "walked", "count": 45618, "sentiment": 0.0}, {"word": "ask", "count": 44128, "sentiment": 0.0}, {"word": "disappointed", "count": 43765, "sentiment": -0.75}, {"word": "wait", "count": 43036, "sentiment": 0.0}, {"word": "put", "count": 42491, "sentiment": 0.0}, {"word": "wrong", "count": 40648, "sentiment": -0.5}, {"word": "many", "count": 39896, "sentiment": 0.5}, {"word": "tasted", "count": 39620, "sentiment": 0.0}, {"word": "sure", "count": 39284, "sentiment": 0.5}, {"word": "gave", "count": 38676, "sentiment": 0.0}, {"word": "looked", "count": 38589, "sentiment": 0.0}, {"word": "nice", "count": 37819, "sentiment": 0.6}, {"word": "tell", "count": 35915, "sentiment": 0.0}, {"word": "decided", "count": 35657, "sentiment": 0.0}, {"word": "arrived", "count": 34945, "sentiment": 0.0}, {"word": "small", "count": 34644, "sentiment": -0.25}, {"word": "seated", "count": 34521, "sentiment": 0.0}, {"word": "leave", "count": 33550, "sentiment": 0.0}, {"word": "sat", "count": 33545, "sentiment": 0.0}, {"word": "old", "count": 33413, "sentiment": 0.1}, {"word": "little", "count": 32749, "sentiment": -0.188}, {"word": "long", "count": 32683, "sentiment": -0.05}, {"word": "served", "count": 32589, "sentiment": 0.0}, {"word": "open", "count": 32309, "sentiment": 0.0}, {"word": "brought", "count": 32275, "sentiment": 0.0}, {"word": "busy", "count": 32065, "sentiment": 0.1}, {"word": "least", "count": 31788, "sentiment": -0.3}, {"word": "poor", "count": 31582, "sentiment": -0.4}, {"word": "used", "count": 31125, "sentiment": 0.0}, {"word": "find", "count": 30626, "sentiment": 0.0}, {"word": "eating", "count": 30354, "sentiment": 0.0}, {"word": "received", "count": 29930, "sentiment": 0.0}, {"word": "coming", "count": 29598, "sentiment": 0.0}, {"word": "cooked", "count": 29388, "sentiment": 0.0}, {"word": "recommend", "count": 29297, "sentiment": 0.0}]}, "2": {"elite": [{"word": "ordered", "count": 40024, "sentiment": 0.0}, {"word": "nice", "count": 18188, "sentiment": 0.6}, {"word": "little", "count": 17031, "sentiment": -0.188}, {"word": "better", "count": 16673, "sentiment": 0.5}, {"word": "going", "count": 15633, "sentiment": 0.0}, {"word": "give", "count": 13937, "sentiment": 0.0}, {"word": "small", "count": 12928, "sentiment": -0.25}, {"word": "tasted", "count": 12903, "sentiment": 0.0}, {"word": "eat", "count": 12829, "sentiment": 0.0}, {"word": "sure", "count": 12646, "sentiment": 0.5}, {"word": "see", "count": 12367, "sentiment": 0.0}, {"word": "many", "count": 11463, "sentiment": 0.5}, {"word": "hot", "count": 10729, "sentiment": 0.25}, {"word": "fried", "count": 10708, "sentiment": 0.0}, {"word": "disappointed", "count": 10638, "sentiment": -0.75}, {"word": "left", "count": 10042, "sentiment": 0.0}, {"word": "seemed", "count": 10014, "sentiment": 0.0}, {"word": "looked", "count": 9871, "sentiment": 0.0}, {"word": "fresh", "count": 9030, "sentiment": 0.3}, {"word": "love", "count": 8878, "sentiment": 0.5}, {"word": "decided", "count": 8747, "sentiment": 0.0}, {"word": "find", "count": 8640, "sentiment": 0.0}, {"word": "cheese", "count": 8638, "sentiment": 0.0}, {"word": "big", "count": 8399, "sentiment": 0.0}, {"word": "dry", "count": 8344, "sentiment": -0.067}, {"word": "special", "count": 8317, "sentiment": 0.357}, {"word": "decent", "count": 8177, "sentiment": 0.167}, {"word": "least", "count": 8168, "sentiment": -0.3}, {"word": "thought", "count": 8144, "sentiment": 0.0}, {"word": "different", "count": 8094, "sentiment": 0.0}, {"word": "looking", "count": 8085, "sentiment": 0.0}, {"word": "served", "count": 8045, "sentiment": 0.0}, {"word": "long", "count": 7806, "sentiment": -0.05}, {"word": "cold", "count": 7802, "sentiment": -0.6}, {"word": "put", "count": 7717, "sentiment": 0.0}, {"word": "cooked", "count": 7700, "sentiment": 0.0}, {"word": "overall", "count": 7459, "sentiment": 0.0}, {"word": "waiting", "count": 7423, "sentiment": 0.0}, {"word": "waited", "count": 7398, "sentiment": 0.0}, {"word": "high", "count": 7355, "sentiment": 0.16}, {"word": "used", "count": 7176, "sentiment": 0.0}, {"word": "ask", "count": 7168, "sentiment": 0.0}, {"word": "busy", "count": 7109, "sentiment": 0.1}, {"word": "seated", "count": 7071, "sentiment": 0.0}, {"word": "wait", "count": 7061, "sentiment": 0.0}, {"word": "old", "count": 7047, "sentiment": 0.1}, {"word": "friendly", "count": 7036, "sentiment": 0.375}, {"word": "large", "count": 6946, "sentiment": 0.214}, {"word": "hard", "count": 6852, "sentiment": -0.292}, {"word": "sweet", "count": 6765, "sentiment": 0.35}], "regular": [{"word": "ordered", "count": 112984, "sentiment": 0.0}, {"word": "nice", "count": 47041, "sentiment": 0.6}, {"word": "going", "count": 43093, "sentiment": 0.0}, {"word": "better", "count": 42502, "sentiment": 0.5}, {"word": "disappointed", "count": 35621, "sentiment": -0.75}, {"word": "little", "count": 34935, "sentiment": -0.188}, {"word": "give", "count": 34636, "sentiment": 0.0}, {"word": "small", "count": 33889, "sentiment": -0.25}, {"word": "eat", "count": 32721, "sentiment": 0.0}, {"word": "tasted", "count": 30844, "sentiment": 0.0}, {"word": "many", "count": 28528, "sentiment": 0.5}, {"word": "left", "count": 28222, "sentiment": 0.0}, {"word": "sure", "count": 27856, "sentiment": 0.5}, {"word": "cold", "count": 27265, "sentiment": -0.6}, {"word": "see", "count": 27155, "sentiment": 0.0}, {"word": "waited", "count": 24316, "sentiment": 0.0}, {"word": "hot", "count": 24059, "sentiment": 0.25}, {"word": "cooked", "count": 23823, "sentiment": 0.0}, {"word": "seemed", "count": 23107, "sentiment": 0.0}, {"word": "ask", "count": 23090, "sentiment": 0.0}, {"word": "wait", "count": 23042, "sentiment": 0.0}, {"word": "served", "count": 22703, "sentiment": 0.0}, {"word": "looked", "count": 22518, "sentiment": 0.0}, {"word": "fried", "count": 22490, "sentiment": 0.0}, {"word": "used", "count": 22341, "sentiment": 0.0}, {"word": "dry", "count": 22180, "sentiment": -0.067}, {"word": "waiting", "count": 22139, "sentiment": 0.0}, {"word": "put", "count": 21171, "sentiment": 0.0}, {"word": "love", "count": 20870, "sentiment": 0.5}, {"word": "seated", "count": 20650, "sentiment": 0.0}, {"word": "long", "count": 20599, "sentiment": -0.05}, {"word": "special", "count": 20426, "sentiment": 0.357}, {"word": "least", "count": 20342, "sentiment": -0.3}, {"word": "fresh", "count": 20221, "sentiment": 0.3}, {"word": "busy", "count": 20003, "sentiment": 0.1}, {"word": "slow", "count": 19879, "sentiment": -0.3}, {"word": "cheese", "count": 19669, "sentiment": 0.0}, {"word": "arrived", "count": 19629, "sentiment": 0.0}, {"word": "brought", "count": 19252, "sentiment": 0.0}, {"word": "gave", "count": 19143, "sentiment": 0.0}, {"word": "looking", "count": 18971, "sentiment": 0.0}, {"word": "decided", "count": 18549, "sentiment": 0.0}, {"word": "different", "count": 18531, "sentiment": 0.0}, {"word": "find", "count": 18455, "sentiment": 0.0}, {"word": "old", "count": 18347, "sentiment": 0.1}, {"word": "decent", "count": 18311, "sentiment": 0.167}, {"word": "disappointing", "count": 18091, "sentiment": -0.6}, {"word": "friendly", "count": 18039, "sentiment": 0.375}, {"word": "high", "count": 18030, "sentiment": 0.16}, {"word": "terrible", "count": 17867, "sentiment": -1.0}]}, "3": {"elite": [{"word": "ordered", "count": 80504, "sentiment": 0.0}, {"word": "nice", "count": 63847, "sentiment": 0.6}, {"word": "little", "count": 61640, "sentiment": -0.188}, {"word": "small", "count": 34596, "sentiment": -0.25}, {"word": "give", "count": 31932, "sentiment": 0.0}, {"word": "better", "count": 31268, "sentiment": 0.5}, {"word": "sure", "count": 29587, "sentiment": 0.5}, {"word": "fried", "count": 29338, "sentiment": 0.0}, {"word": "decent", "count": 29120, "sentiment": 0.167}, {"word": "going", "count": 29029, "sentiment": 0.0}, {"word": "hot", "count": 28963, "sentiment": 0.25}, {"word": "delicious", "count": 28645, "sentiment": 1.0}, {"word": "see", "count": 27806, "sentiment": 0.0}, {"word": "eat", "count": 27670, "sentiment": 0.0}, {"word": "fresh", "count": 27386, "sentiment": 0.3}, {"word": "overall", "count": 27062, "sentiment": 0.0}, {"word": "love", "count": 26432, "sentiment": 0.5}, {"word": "friendly", "count": 26237, "sentiment": 0.375}, {"word": "many", "count": 25505, "sentiment": 0.5}, {"word": "big", "count": 23478, "sentiment": 0.0}, {"word": "special", "count": 22890, "sentiment": 0.357}, {"word": "large", "count": 22707, "sentiment": 0.214}, {"word": "different", "count": 22564, "sentiment": 0.0}, {"word": "tasty", "count": 22470, "sentiment": 0.0}, {"word": "cheese", "count": 22449, "sentiment": 0.0}, {"word": "find", "count": 22316, "sentiment": 0.0}, {"word": "tasted", "count": 21219, "sentiment": 0.0}, {"word": "seemed", "count": 20847, "sentiment": 0.0}, {"word": "sweet", "count": 20426, "sentiment": 0.35}, {"word": "happy", "count": 20390, "sentiment": 0.8}, {"word": "looking", "count": 19308, "sentiment": 0.0}, {"word": "thought", "count": 19133, "sentiment": 0.0}, {"word": "served", "count": 18250, "sentiment": 0.0}, {"word": "enjoyed", "count": 17753, "sentiment": 0.5}, {"word": "super", "count": 17653, "sentiment": 0.333}, {"word": "busy", "count": 17492, "sentiment": 0.1}, {"word": "decided", "count": 17447, "sentiment": 0.0}, {"word": "cooked", "count": 17307, "sentiment": 0.0}, {"word": "huge", "count": 17191, "sentiment": 0.4}, {"word": "high", "count": 16577, "sentiment": 0.16}, {"word": "looked", "count": 16518, "sentiment": 0.0}, {"word": "full", "count": 16502, "sentiment": 0.35}, {"word": "found", "count": 15894, "sentiment": 0.0}, {"word": "fine", "count": 15842, "sentiment": 0.417}, {"word": "long", "count": 15443, "sentiment": -0.05}, {"word": "liked", "count": 15396, "sentiment": 0.6}, {"word": "open", "count": 15194, "sentiment": 0.0}, {"word": "average", "count": 14724, "sentiment": -0.15}, {"word": "disappointed", "count": 14595, "sentiment": -0.75}, {"word": "amazing", "count": 14592, "sentiment": 0.6}], "regular": [{"word": "ordered", "count": 84622, "sentiment": 0.0}, {"word": "nice", "count": 67669, "sentiment": 0.6}, {"word": "little", "count": 55423, "sentiment": -0.188}, {"word": "better", "count": 36319, "sentiment": 0.5}, {"word": "give", "count": 35637, "sentiment": 0.0}, {"word": "small", "count": 35010, "sentiment": -0.25}, {"word": "delicious", "count": 30383, "sentiment": 1.0}, {"word": "going", "count": 29868, "sentiment": 0.0}, {"word": "friendly", "count": 28951, "sentiment": 0.375}, {"word": "eat", "count": 28753, "sentiment": 0.0}, {"word": "sure", "count": 26704, "sentiment": 0.5}, {"word": "love", "count": 26695, "sentiment": 0.5}, {"word": "decent", "count": 26370, "sentiment": 0.167}, {"word": "fresh", "count": 25892, "sentiment": 0.3}, {"word": "overall", "count": 25871, "sentiment": 0.0}, {"word": "fried", "count": 25575, "sentiment": 0.0}, {"word": "hot", "count": 25486, "sentiment": 0.25}, {"word": "see", "count": 23970, "sentiment": 0.0}, {"word": "many", "count": 23928, "sentiment": 0.5}, {"word": "special", "count": 22854, "sentiment": 0.357}, {"word": "tasty", "count": 22102, "sentiment": 0.0}, {"word": "tasted", "count": 21244, "sentiment": 0.0}, {"word": "disappointed", "count": 20666, "sentiment": -0.75}, {"word": "seemed", "count": 20610, "sentiment": 0.0}, {"word": "different", "count": 20161, "sentiment": 0.0}, {"word": "cooked", "count": 19731, "sentiment": 0.0}, {"word": "big", "count": 19652, "sentiment": 0.0}, {"word": "cheese", "count": 19325, "sentiment": 0.0}, {"word": "busy", "count": 19104, "sentiment": 0.1}, {"word": "amazing", "count": 18838, "sentiment": 0.6}, {"word": "wait", "count": 18657, "sentiment": 0.0}, {"word": "find", "count": 18046, "sentiment": 0.0}, {"word": "average", "count": 17989, "sentiment": -0.15}, {"word": "served", "count": 17983, "sentiment": 0.0}, {"word": "looking", "count": 17931, "sentiment": 0.0}, {"word": "high", "count": 17640, "sentiment": 0.16}, {"word": "large", "count": 17170, "sentiment": 0.214}, {"word": "left", "count": 16990, "sentiment": 0.0}, {"word": "slow", "count": 16976, "sentiment": -0.3}, {"word": "thought", "count": 16763, "sentiment": 0.0}, {"word": "excellent", "count": 16461, "sentiment": 1.0}, {"word": "long", "count": 16363, "sentiment": -0.05}, {"word": "happy", "count": 16103, "sentiment": 0.8}, {"word": "sweet", "count": 16076, "sentiment": 0.35}, {"word": "used", "count": 16006, "sentiment": 0.0}, {"word": "dry", "count": 15885, "sentiment": -0.067}, {"word": "seated", "count": 15826, "sentiment": 0.0}, {"word": "fine", "count": 15617, "sentiment": 0.417}, {"word": "looked", "count": 15500, "sentiment": 0.0}, {"word": "ask", "count": 15456, "sentiment": 0.0}]}, "4": {"elite": [{"word": "nice", "count": 140145, "sentiment": 0.6}, {"word": "ordered", "count": 137611, "sentiment": 0.0}, {"word": "delicious", "count": 132942, "sentiment": 1.0}, {"word": "little", "count": 130363, "sentiment": -0.188}, {"word": "fresh", "count": 84559, "sentiment": 0.3}, {"word": "love", "count": 81827, "sentiment": 0.5}, {"word": "friendly", "count": 72242, "sentiment": 0.375}, {"word": "small", "count": 71180, "sentiment": -0.25}, {"word": "hot", "count": 65448, "sentiment": 0.25}, {"word": "fried", "count": 63906, "sentiment": 0.0}, {"word": "tasty", "count": 57654, "sentiment": 0.0}, {"word": "happy", "count": 56595, "sentiment": 0.8}, {"word": "eat", "count": 56026, "sentiment": 0.0}, {"word": "enjoyed", "count": 55236, "sentiment": 0.5}, {"word": "sure", "count": 55071, "sentiment": 0.5}, {"word": "amazing", "count": 52522, "sentiment": 0.6}, {"word": "many", "count": 52492, "sentiment": 0.5}, {"word": "see", "count": 52231, "sentiment": 0.0}, {"word": "big", "count": 51730, "sentiment": 0.0}, {"word": "large", "count": 51480, "sentiment": 0.214}, {"word": "sweet", "count": 51443, "sentiment": 0.35}, {"word": "going", "count": 51036, "sentiment": 0.0}, {"word": "different", "count": 49033, "sentiment": 0.0}, {"word": "cheese", "count": 48699, "sentiment": 0.0}, {"word": "find", "count": 47679, "sentiment": 0.0}, {"word": "super", "count": 46326, "sentiment": 0.333}, {"word": "recommend", "count": 45347, "sentiment": 0.0}, {"word": "favorite", "count": 45103, "sentiment": 0.5}, {"word": "huge", "count": 44059, "sentiment": 0.4}, {"word": "perfect", "count": 43881, "sentiment": 1.0}, {"word": "full", "count": 43574, "sentiment": 0.35}, {"word": "give", "count": 43481, "sentiment": 0.0}, {"word": "overall", "count": 43011, "sentiment": 0.0}, {"word": "looking", "count": 41322, "sentiment": 0.0}, {"word": "loved", "count": 39820, "sentiment": 0.7}, {"word": "served", "count": 39322, "sentiment": 0.0}, {"word": "excellent", "count": 38011, "sentiment": 1.0}, {"word": "special", "count": 37857, "sentiment": 0.357}, {"word": "better", "count": 37850, "sentiment": 0.5}, {"word": "awesome", "count": 35983, "sentiment": 1.0}, {"word": "cooked", "count": 35322, "sentiment": 0.0}, {"word": "busy", "count": 34904, "sentiment": 0.1}, {"word": "enjoy", "count": 34630, "sentiment": 0.4}, {"word": "decided", "count": 34345, "sentiment": 0.0}, {"word": "open", "count": 33606, "sentiment": 0.0}, {"word": "free", "count": 33605, "sentiment": 0.4}, {"word": "right", "count": 32877, "sentiment": 0.286}, {"word": "quick", "count": 31856, "sentiment": 0.333}, {"word": "liked", "count": 30942, "sentiment": 0.6}, {"word": "found", "count": 30554, "sentiment": 0.0}], "regular": [{"word": "nice", "count": 140994, "sentiment": 0.6}, {"word": "delicious", "count": 138585, "sentiment": 1.0}, {"word": "little", "count": 119332, "sentiment": -0.188}, {"word": "ordered", "count": 109911, "sentiment": 0.0}, {"word": "friendly", "count": 89559, "sentiment": 0.375}, {"word": "fresh", "count": 81935, "sentiment": 0.3}, {"word": "love", "count": 80933, "sentiment": 0.5}, {"word": "excellent", "count": 66162, "sentiment": 1.0}, {"word": "amazing", "count": 65344, "sentiment": 0.6}, {"word": "recommend", "count": 58995, "sentiment": 0.0}, {"word": "small", "count": 57620, "sentiment": -0.25}, {"word": "tasty", "count": 56298, "sentiment": 0.0}, {"word": "hot", "count": 53966, "sentiment": 0.25}, {"word": "eat", "count": 53160, "sentiment": 0.0}, {"word": "fried", "count": 52941, "sentiment": 0.0}, {"word": "enjoyed", "count": 48817, "sentiment": 0.5}, {"word": "going", "count": 46366, "sentiment": 0.0}, {"word": "give", "count": 44975, "sentiment": 0.0}, {"word": "awesome", "count": 44320, "sentiment": 1.0}, {"word": "sure", "count": 42804, "sentiment": 0.5}, {"word": "happy", "count": 42640, "sentiment": 0.8}, {"word": "overall", "count": 40218, "sentiment": 0.0}, {"word": "many", "count": 40012, "sentiment": 0.5}, {"word": "big", "count": 39532, "sentiment": 0.0}, {"word": "loved", "count": 39000, "sentiment": 0.7}, {"word": "favorite", "count": 38461, "sentiment": 0.5}, {"word": "cheese", "count": 37944, "sentiment": 0.0}, {"word": "better", "count": 37706, "sentiment": 0.5}, {"word": "large", "count": 36765, "sentiment": 0.214}, {"word": "different", "count": 36672, "sentiment": 0.0}, {"word": "sweet", "count": 35906, "sentiment": 0.35}, {"word": "perfect", "count": 35854, "sentiment": 1.0}, {"word": "super", "count": 35356, "sentiment": 0.333}, {"word": "find", "count": 34870, "sentiment": 0.0}, {"word": "looking", "count": 34823, "sentiment": 0.0}, {"word": "see", "count": 34299, "sentiment": 0.0}, {"word": "busy", "count": 33361, "sentiment": 0.1}, {"word": "cooked", "count": 33239, "sentiment": 0.0}, {"word": "special", "count": 32613, "sentiment": 0.357}, {"word": "huge", "count": 32481, "sentiment": 0.4}, {"word": "clean", "count": 31248, "sentiment": 0.367}, {"word": "full", "count": 30653, "sentiment": 0.35}, {"word": "attentive", "count": 30026, "sentiment": 0.4}, {"word": "quick", "count": 29682, "sentiment": 0.333}, {"word": "served", "count": 28788, "sentiment": 0.0}, {"word": "wait", "count": 28371, "sentiment": 0.0}, {"word": "fantastic", "count": 27662, "sentiment": 0.4}, {"word": "enjoy", "count": 27493, "sentiment": 0.4}, {"word": "local", "count": 26368, "sentiment": 0.0}, {"word": "found", "count": 25991, "sentiment": 0.0}]}, "5": {"elite": [{"word": "delicious", "count": 173635, "sentiment": 1.0}, {"word": "ordered", "count": 116680, "sentiment": 0.0}, {"word": "love", "count": 114845, "sentiment": 0.5}, {"word": "amazing", "count": 113979, "sentiment": 0.6}, {"word": "nice", "count": 100060, "sentiment": 0.6}, {"word": "fresh", "count": 96236, "sentiment": 0.3}, {"word": "little", "count": 90675, "sentiment": -0.188}, {"word": "friendly", "count": 76909, "sentiment": 0.375}, {"word": "favorite", "count": 72376, "sentiment": 0.5}, {"word": "perfect", "count": 68514, "sentiment": 1.0}, {"word": "recommend", "count": 61573, "sentiment": 0.0}, {"word": "hot", "count": 59029, "sentiment": 0.25}, {"word": "super", "count": 57059, "sentiment": 0.333}, {"word": "small", "count": 56787, "sentiment": -0.25}, {"word": "fried", "count": 56456, "sentiment": 0.0}, {"word": "eat", "count": 56089, "sentiment": 0.0}, {"word": "many", "count": 55749, "sentiment": 0.5}, {"word": "sweet", "count": 54448, "sentiment": 0.35}, {"word": "happy", "count": 53068, "sentiment": 0.8}, {"word": "loved", "count": 52157, "sentiment": 0.7}, {"word": "sure", "count": 51612, "sentiment": 0.5}, {"word": "awesome", "count": 51048, "sentiment": 1.0}, {"word": "going", "count": 49137, "sentiment": 0.0}, {"word": "see", "count": 47312, "sentiment": 0.0}, {"word": "excellent", "count": 46359, "sentiment": 1.0}, {"word": "different", "count": 46177, "sentiment": 0.0}, {"word": "cheese", "count": 45713, "sentiment": 0.0}, {"word": "find", "count": 44440, "sentiment": 0.0}, {"word": "full", "count": 42941, "sentiment": 0.35}, {"word": "big", "count": 41442, "sentiment": 0.0}, {"word": "huge", "count": 40998, "sentiment": 0.4}, {"word": "enjoyed", "count": 40726, "sentiment": 0.5}, {"word": "tasty", "count": 39431, "sentiment": 0.0}, {"word": "large", "count": 39178, "sentiment": 0.214}, {"word": "special", "count": 37611, "sentiment": 0.357}, {"word": "looking", "count": 37347, "sentiment": 0.0}, {"word": "free", "count": 35052, "sentiment": 0.4}, {"word": "fantastic", "count": 34842, "sentiment": 0.4}, {"word": "served", "count": 34742, "sentiment": 0.0}, {"word": "give", "count": 34269, "sentiment": 0.0}, {"word": "cooked", "count": 34045, "sentiment": 0.0}, {"word": "local", "count": 33791, "sentiment": 0.0}, {"word": "enjoy", "count": 32991, "sentiment": 0.4}, {"word": "right", "count": 32941, "sentiment": 0.286}, {"word": "wonderful", "count": 32562, "sentiment": 1.0}, {"word": "open", "count": 31972, "sentiment": 0.0}, {"word": "coming", "count": 31404, "sentiment": 0.0}, {"word": "top", "count": 30152, "sentiment": 0.5}, {"word": "decided", "count": 29160, "sentiment": 0.0}, {"word": "found", "count": 29072, "sentiment": 0.0}], "regular": [{"word": "delicious", "count": 423411, "sentiment": 1.0}, {"word": "amazing", "count": 376407, "sentiment": 0.6}, {"word": "love", "count": 262611, "sentiment": 0.5}, {"word": "friendly", "count": 246419, "sentiment": 0.375}, {"word": "fresh", "count": 219836, "sentiment": 0.3}, {"word": "nice", "count": 212515, "sentiment": 0.6}, {"word": "recommend", "count": 204613, "sentiment": 0.0}, {"word": "ordered", "count": 183697, "sentiment": 0.0}, {"word": "excellent", "count": 182046, "sentiment": 1.0}, {"word": "awesome", "count": 161634, "sentiment": 1.0}, {"word": "favorite", "count": 157013, "sentiment": 0.5}, {"word": "little", "count": 141598, "sentiment": -0.188}, {"word": "perfect", "count": 125617, "sentiment": 1.0}, {"word": "eat", "count": 120893, "sentiment": 0.0}, {"word": "super", "count": 114262, "sentiment": 0.333}, {"word": "loved", "count": 112561, "sentiment": 0.7}, {"word": "wonderful", "count": 109612, "sentiment": 1.0}, {"word": "fantastic", "count": 109200, "sentiment": 0.4}, {"word": "hot", "count": 101130, "sentiment": 0.25}, {"word": "going", "count": 99567, "sentiment": 0.0}, {"word": "sure", "count": 96451, "sentiment": 0.5}, {"word": "happy", "count": 95934, "sentiment": 0.8}, {"word": "fried", "count": 94344, "sentiment": 0.0}, {"word": "many", "count": 92029, "sentiment": 0.5}, {"word": "small", "count": 80902, "sentiment": -0.25}, {"word": "looking", "count": 76179, "sentiment": 0.0}, {"word": "tasty", "count": 76042, "sentiment": 0.0}, {"word": "sweet", "count": 75425, "sentiment": 0.35}, {"word": "coming", "count": 74496, "sentiment": 0.0}, {"word": "special", "count": 73975, "sentiment": 0.357}, {"word": "enjoyed", "count": 72989, "sentiment": 0.5}, {"word": "find", "count": 72699, "sentiment": 0.0}, {"word": "cheese", "count": 71362, "sentiment": 0.0}, {"word": "attentive", "count": 70368, "sentiment": 0.4}, {"word": "different", "count": 70019, "sentiment": 0.0}, {"word": "clean", "count": 69301, "sentiment": 0.367}, {"word": "give", "count": 66237, "sentiment": 0.0}, {"word": "see", "count": 65679, "sentiment": 0.0}, {"word": "big", "count": 65074, "sentiment": 0.0}, {"word": "local", "count": 64102, "sentiment": 0.0}, {"word": "better", "count": 63759, "sentiment": 0.5}, {"word": "found", "count": 63538, "sentiment": 0.0}, {"word": "cooked", "count": 63123, "sentiment": 0.0}, {"word": "huge", "count": 61555, "sentiment": 0.4}, {"word": "full", "count": 60494, "sentiment": 0.35}, {"word": "top", "count": 58521, "sentiment": 0.5}, {"word": "large", "count": 56937, "sentiment": 0.214}, {"word": "free", "count": 56242, "sentiment": 0.4}, {"word": "disappointed", "count": 56012, "sentiment": -0.75}, {"word": "helpful", "count": 54980, "sentiment": 0.0}]}}}