{"meta": {"total_reviews": 5101, "total_elite_reviews": 1334, "total_regular_reviews": 3767, "business_count": 85, "city": "Chesterfield", "state": "MO"}, "star_counts": {"1": {"elite": 56, "regular": 654, "total": 710, "elite_pct": 7.9}, "2": {"elite": 89, "regular": 346, "total": 435, "elite_pct": 20.5}, "3": {"elite": 248, "regular": 321, "total": 569, "elite_pct": 43.6}, "4": {"elite": 452, "regular": 664, "total": 1116, "elite_pct": 40.5}, "5": {"elite": 489, "regular": 1782, "total": 2271, "elite_pct": 21.5}}, "trajectories": {"strong": {"regular": {"1": {"avg": 4.55, "count": 20}, "3": {"avg": 4.509, "count": 19}, "5": {"avg": 4.611, "count": 18}, "10": {"avg": 4.573, "count": 15}, "25": {"avg": 4.444, "count": 9}, "50": {"avg": 4.34, "count": 5}, "100": {"avg": 4.35, "count": 4}}, "all": {"1": {"avg": 4.6, "count": 20}, "3": {"avg": 4.483, "count": 20}, "5": {"avg": 4.54, "count": 20}, "10": {"avg": 4.5, "count": 18}, "25": {"avg": 4.447, "count": 11}, "50": {"avg": 4.403, "count": 7}, "100": {"avg": 4.332, "count": 4}}, "elite": {"1": {"avg": 4.65, "count": 20}, "3": {"avg": 4.439, "count": 19}, "5": {"avg": 4.427, "count": 15}, "10": {"avg": 4.391, "count": 11}, "25": {"avg": 4.42, "count": 6}, "50": {"avg": 4.3, "count": 1}, "100": {"avg": 4.13, "count": 1}}}, "average": {"regular": {"1": {"avg": 3.609, "count": 23}, "3": {"avg": 3.606, "count": 22}, "5": {"avg": 3.418, "count": 22}, "10": {"avg": 3.565, "count": 17}, "25": {"avg": 3.507, "count": 12}, "50": {"avg": 3.435, "count": 8}, "100": {"avg": 3.45, "count": 2}}, "all": {"1": {"avg": 3.739, "count": 23}, "3": {"avg": 3.768, "count": 23}, "5": {"avg": 3.548, "count": 23}, "10": {"avg": 3.468, "count": 19}, "25": {"avg": 3.543, "count": 14}, "50": {"avg": 3.505, "count": 12}, "100": {"avg": 3.405, "count": 4}}, "elite": {"1": {"avg": 3.696, "count": 23}, "3": {"avg": 3.55, "count": 20}, "5": {"avg": 3.624, "count": 17}, "10": {"avg": 3.554, "count": 13}, "25": {"avg": 3.78, "count": 4}}}, "weak": {"regular": {"1": {"avg": 3.2, "count": 15}, "3": {"avg": 3.178, "count": 15}, "5": {"avg": 3.133, "count": 15}, "10": {"avg": 3.262, "count": 13}, "25": {"avg": 3.16, "count": 5}, "50": {"avg": 3.06, "count": 2}, "100": {"avg": 2.935, "count": 2}}, "all": {"1": {"avg": 3.867, "count": 15}, "3": {"avg": 3.378, "count": 15}, "5": {"avg": 3.413, "count": 15}, "10": {"avg": 3.3, "count": 15}, "25": {"avg": 3.227, "count": 9}, "50": {"avg": 3.235, "count": 4}, "100": {"avg": 2.945, "count": 2}}, "elite": {"1": {"avg": 3.8, "count": 15}, "3": {"avg": 3.422, "count": 15}, "5": {"avg": 3.35, "count": 12}, "10": {"avg": 3.367, "count": 6}, "25": {"avg": 3.16, "count": 2}}}, "poor": {"regular": {"1": {"avg": 3.75, "count": 8}, "3": {"avg": 2.75, "count": 8}, "5": {"avg": 2.375, "count": 8}, "10": {"avg": 2.025, "count": 4}, "25": {"avg": 1.82, "count": 4}, "50": {"avg": 1.4, "count": 1}}, "all": {"1": {"avg": 3.5, "count": 8}, "3": {"avg": 3.208, "count": 8}, "5": {"avg": 2.975, "count": 8}, "10": {"avg": 2.76, "count": 5}, "25": {"avg": 2.14, "count": 4}, "50": {"avg": 2.09, "count": 2}}, "elite": {"1": {"avg": 4.0, "count": 8}, "3": {"avg": 3.333, "count": 6}, "5": {"avg": 3.24, "count": 5}, "10": {"avg": 2.867, "count": 3}}}, "good": {"regular": {"1": {"avg": 4.316, "count": 19}, "3": {"avg": 4.105, "count": 19}, "5": {"avg": 4.105, "count": 19}, "10": {"avg": 3.838, "count": 16}, "25": {"avg": 3.923, "count": 13}, "50": {"avg": 3.932, "count": 10}, "100": {"avg": 3.915, "count": 2}}, "all": {"1": {"avg": 4.105, "count": 19}, "3": {"avg": 4.088, "count": 19}, "5": {"avg": 4.105, "count": 19}, "10": {"avg": 4.05, "count": 18}, "25": {"avg": 3.935, "count": 16}, "50": {"avg": 3.89, "count": 12}, "100": {"avg": 3.94, "count": 4}}, "elite": {"1": {"avg": 3.722, "count": 18}, "3": {"avg": 3.963, "count": 18}, "5": {"avg": 4.059, "count": 17}, "10": {"avg": 4.107, "count": 14}, "25": {"avg": 4.048, "count": 5}, "50": {"avg": 4.11, "count": 2}}}}, "words": {"1": {"elite": [{"word": "ordered", "count": 22, "sentiment": 0.0}, {"word": "waited", "count": 16, "sentiment": 0.0}, {"word": "give", "count": 14, "sentiment": 0.0}, {"word": "left", "count": 12, "sentiment": 0.0}, {"word": "going", "count": 10, "sentiment": 0.0}, {"word": "cheese", "count": 10, "sentiment": 0.0}, {"word": "called", "count": 10, "sentiment": 0.0}, {"word": "seated", "count": 9, "sentiment": 0.0}, {"word": "pay", "count": 9, "sentiment": 0.0}, {"word": "worst", "count": 9, "sentiment": -1.0}, {"word": "different", "count": 9, "sentiment": 0.0}, {"word": "cold", "count": 9, "sentiment": -0.6}, {"word": "small", "count": 9, "sentiment": -0.25}, {"word": "wrong", "count": 8, "sentiment": -0.5}, {"word": "due", "count": 8, "sentiment": -0.125}, {"word": "least", "count": 8, "sentiment": -0.3}, {"word": "found", "count": 8, "sentiment": 0.0}, {"word": "second", "count": 7, "sentiment": 0.0}, {"word": "disappointed", "count": 7, "sentiment": -0.75}, {"word": "used", "count": 7, "sentiment": 0.0}, {"word": "sitting", "count": 7, "sentiment": 0.0}, {"word": "sure", "count": 7, "sentiment": 0.5}, {"word": "see", "count": 7, "sentiment": 0.0}, {"word": "long", "count": 7, "sentiment": -0.05}, {"word": "says", "count": 7, "sentiment": 0.0}, {"word": "better", "count": 6, "sentiment": 0.5}, {"word": "little", "count": 6, "sentiment": -0.188}, {"word": "open", "count": 6, "sentiment": 0.0}, {"word": "many", "count": 6, "sentiment": 0.5}, {"word": "tell", "count": 6, "sentiment": 0.0}, {"word": "looked", "count": 6, "sentiment": 0.0}, {"word": "cooked", "count": 6, "sentiment": 0.0}, {"word": "ask", "count": 6, "sentiment": 0.0}, {"word": "given", "count": 6, "sentiment": 0.0}, {"word": "single", "count": 6, "sentiment": -0.071}, {"word": "getting", "count": 5, "sentiment": 0.0}, {"word": "full", "count": 5, "sentiment": 0.35}, {"word": "nice", "count": 5, "sentiment": 0.6}, {"word": "seemed", "count": 5, "sentiment": 0.0}, {"word": "walked", "count": 5, "sentiment": 0.0}, {"word": "able", "count": 5, "sentiment": 0.5}, {"word": "love", "count": 5, "sentiment": 0.5}, {"word": "fresh", "count": 5, "sentiment": 0.3}, {"word": "pulled", "count": 5, "sentiment": 0.0}, {"word": "leave", "count": 5, "sentiment": 0.0}, {"word": "bring", "count": 5, "sentiment": 0.0}, {"word": "decided", "count": 5, "sentiment": 0.0}, {"word": "sat", "count": 5, "sentiment": 0.0}, {"word": "wait", "count": 5, "sentiment": 0.0}, {"word": "waiting", "count": 5, "sentiment": 0.0}], "regular": [{"word": "ordered", "count": 226, "sentiment": 0.0}, {"word": "going", "count": 118, "sentiment": 0.0}, {"word": "worst", "count": 85, "sentiment": -1.0}, {"word": "give", "count": 78, "sentiment": 0.0}, {"word": "left", "count": 77, "sentiment": 0.0}, {"word": "terrible", "count": 76, "sentiment": -1.0}, {"word": "waited", "count": 75, "sentiment": 0.0}, {"word": "called", "count": 73, "sentiment": 0.0}, {"word": "horrible", "count": 73, "sentiment": -1.0}, {"word": "eat", "count": 65, "sentiment": 0.0}, {"word": "waiting", "count": 57, "sentiment": 0.0}, {"word": "rude", "count": 56, "sentiment": -0.3}, {"word": "wrong", "count": 56, "sentiment": -0.5}, {"word": "put", "count": 55, "sentiment": 0.0}, {"word": "small", "count": 53, "sentiment": -0.25}, {"word": "see", "count": 52, "sentiment": 0.0}, {"word": "sure", "count": 50, "sentiment": 0.5}, {"word": "thought", "count": 49, "sentiment": 0.0}, {"word": "walked", "count": 49, "sentiment": 0.0}, {"word": "poor", "count": 49, "sentiment": -0.4}, {"word": "used", "count": 48, "sentiment": 0.0}, {"word": "better", "count": 47, "sentiment": 0.5}, {"word": "cold", "count": 47, "sentiment": -0.6}, {"word": "gave", "count": 46, "sentiment": 0.0}, {"word": "wait", "count": 46, "sentiment": 0.0}, {"word": "long", "count": 45, "sentiment": -0.05}, {"word": "seated", "count": 45, "sentiment": 0.0}, {"word": "many", "count": 44, "sentiment": 0.5}, {"word": "disappointed", "count": 44, "sentiment": -0.75}, {"word": "find", "count": 44, "sentiment": 0.0}, {"word": "brought", "count": 44, "sentiment": 0.0}, {"word": "several", "count": 43, "sentiment": 0.0}, {"word": "arrived", "count": 43, "sentiment": 0.0}, {"word": "little", "count": 43, "sentiment": -0.188}, {"word": "nice", "count": 43, "sentiment": 0.6}, {"word": "cheese", "count": 42, "sentiment": 0.0}, {"word": "open", "count": 42, "sentiment": 0.0}, {"word": "fried", "count": 42, "sentiment": 0.0}, {"word": "received", "count": 42, "sentiment": 0.0}, {"word": "hot", "count": 42, "sentiment": 0.25}, {"word": "tell", "count": 41, "sentiment": 0.0}, {"word": "leave", "count": 40, "sentiment": 0.0}, {"word": "ask", "count": 40, "sentiment": 0.0}, {"word": "old", "count": 39, "sentiment": 0.1}, {"word": "busy", "count": 39, "sentiment": 0.1}, {"word": "decided", "count": 39, "sentiment": 0.0}, {"word": "pay", "count": 39, "sentiment": 0.0}, {"word": "looked", "count": 38, "sentiment": 0.0}, {"word": "getting", "count": 38, "sentiment": 0.0}, {"word": "least", "count": 38, "sentiment": -0.3}]}, "2": {"elite": [{"word": "ordered", "count": 45, "sentiment": 0.0}, {"word": "better", "count": 25, "sentiment": 0.5}, {"word": "sweet", "count": 18, "sentiment": 0.35}, {"word": "cheese", "count": 15, "sentiment": 0.0}, {"word": "sure", "count": 15, "sentiment": 0.5}, {"word": "hot", "count": 15, "sentiment": 0.25}, {"word": "give", "count": 14, "sentiment": 0.0}, {"word": "fried", "count": 14, "sentiment": 0.0}, {"word": "cooked", "count": 13, "sentiment": 0.0}, {"word": "small", "count": 13, "sentiment": -0.25}, {"word": "going", "count": 12, "sentiment": 0.0}, {"word": "many", "count": 12, "sentiment": 0.5}, {"word": "decent", "count": 11, "sentiment": 0.167}, {"word": "nice", "count": 11, "sentiment": 0.6}, {"word": "used", "count": 10, "sentiment": 0.0}, {"word": "eating", "count": 9, "sentiment": 0.0}, {"word": "see", "count": 9, "sentiment": 0.0}, {"word": "special", "count": 9, "sentiment": 0.357}, {"word": "looking", "count": 9, "sentiment": 0.0}, {"word": "large", "count": 9, "sentiment": 0.214}, {"word": "thought", "count": 9, "sentiment": 0.0}, {"word": "deep", "count": 9, "sentiment": 0.0}, {"word": "use", "count": 8, "sentiment": 0.0}, {"word": "cold", "count": 8, "sentiment": -0.6}, {"word": "little", "count": 8, "sentiment": -0.188}, {"word": "eat", "count": 8, "sentiment": 0.0}, {"word": "looked", "count": 8, "sentiment": 0.0}, {"word": "served", "count": 8, "sentiment": 0.0}, {"word": "put", "count": 8, "sentiment": 0.0}, {"word": "brought", "count": 8, "sentiment": 0.0}, {"word": "arrived", "count": 7, "sentiment": 0.0}, {"word": "seated", "count": 7, "sentiment": 0.0}, {"word": "disappointing", "count": 7, "sentiment": -0.6}, {"word": "decided", "count": 7, "sentiment": 0.0}, {"word": "expect", "count": 7, "sentiment": 0.0}, {"word": "busy", "count": 7, "sentiment": 0.1}, {"word": "available", "count": 7, "sentiment": 0.4}, {"word": "baked", "count": 7, "sentiment": 0.0}, {"word": "crispy", "count": 7, "sentiment": 0.0}, {"word": "bread", "count": 7, "sentiment": 0.0}, {"word": "gave", "count": 7, "sentiment": 0.0}, {"word": "filled", "count": 7, "sentiment": 0.4}, {"word": "mexican", "count": 7, "sentiment": 0.0}, {"word": "chinese", "count": 7, "sentiment": 0.0}, {"word": "long", "count": 7, "sentiment": -0.05}, {"word": "worth", "count": 6, "sentiment": 0.3}, {"word": "left", "count": 6, "sentiment": 0.0}, {"word": "old", "count": 6, "sentiment": 0.1}, {"word": "stopped", "count": 6, "sentiment": 0.0}, {"word": "enjoyed", "count": 6, "sentiment": 0.5}], "regular": [{"word": "ordered", "count": 139, "sentiment": 0.0}, {"word": "small", "count": 43, "sentiment": -0.25}, {"word": "going", "count": 42, "sentiment": 0.0}, {"word": "better", "count": 41, "sentiment": 0.5}, {"word": "little", "count": 38, "sentiment": -0.188}, {"word": "ask", "count": 37, "sentiment": 0.0}, {"word": "long", "count": 36, "sentiment": -0.05}, {"word": "special", "count": 34, "sentiment": 0.357}, {"word": "nice", "count": 34, "sentiment": 0.6}, {"word": "eat", "count": 33, "sentiment": 0.0}, {"word": "cold", "count": 33, "sentiment": -0.6}, {"word": "many", "count": 32, "sentiment": 0.5}, {"word": "disappointed", "count": 30, "sentiment": -0.75}, {"word": "left", "count": 30, "sentiment": 0.0}, {"word": "seemed", "count": 30, "sentiment": 0.0}, {"word": "hot", "count": 29, "sentiment": 0.25}, {"word": "brought", "count": 29, "sentiment": 0.0}, {"word": "thought", "count": 29, "sentiment": 0.0}, {"word": "wait", "count": 28, "sentiment": 0.0}, {"word": "served", "count": 28, "sentiment": 0.0}, {"word": "tasted", "count": 28, "sentiment": 0.0}, {"word": "used", "count": 28, "sentiment": 0.0}, {"word": "cooked", "count": 27, "sentiment": 0.0}, {"word": "cheese", "count": 26, "sentiment": 0.0}, {"word": "looked", "count": 26, "sentiment": 0.0}, {"word": "fresh", "count": 26, "sentiment": 0.3}, {"word": "love", "count": 26, "sentiment": 0.5}, {"word": "least", "count": 25, "sentiment": -0.3}, {"word": "large", "count": 24, "sentiment": 0.214}, {"word": "fried", "count": 24, "sentiment": 0.0}, {"word": "sat", "count": 24, "sentiment": 0.0}, {"word": "old", "count": 24, "sentiment": 0.1}, {"word": "dry", "count": 23, "sentiment": -0.067}, {"word": "see", "count": 23, "sentiment": 0.0}, {"word": "give", "count": 23, "sentiment": 0.0}, {"word": "arrived", "count": 22, "sentiment": 0.0}, {"word": "find", "count": 22, "sentiment": 0.0}, {"word": "sure", "count": 22, "sentiment": 0.5}, {"word": "extra", "count": 22, "sentiment": 0.0}, {"word": "called", "count": 21, "sentiment": 0.0}, {"word": "ready", "count": 21, "sentiment": 0.2}, {"word": "eating", "count": 21, "sentiment": 0.0}, {"word": "waiting", "count": 21, "sentiment": 0.0}, {"word": "poor", "count": 21, "sentiment": -0.4}, {"word": "decided", "count": 20, "sentiment": 0.0}, {"word": "paid", "count": 20, "sentiment": 0.0}, {"word": "fine", "count": 20, "sentiment": 0.417}, {"word": "walked", "count": 19, "sentiment": 0.0}, {"word": "mexican", "count": 19, "sentiment": 0.0}, {"word": "ate", "count": 19, "sentiment": 0.0}]}, "3": {"elite": [{"word": "ordered", "count": 110, "sentiment": 0.0}, {"word": "little", "count": 79, "sentiment": -0.188}, {"word": "nice", "count": 63, "sentiment": 0.6}, {"word": "hot", "count": 60, "sentiment": 0.25}, {"word": "small", "count": 46, "sentiment": -0.25}, {"word": "excellent", "count": 43, "sentiment": 1.0}, {"word": "large", "count": 43, "sentiment": 0.214}, {"word": "many", "count": 37, "sentiment": 0.5}, {"word": "sweet", "count": 35, "sentiment": 0.35}, {"word": "fresh", "count": 35, "sentiment": 0.3}, {"word": "cheese", "count": 34, "sentiment": 0.0}, {"word": "fried", "count": 34, "sentiment": 0.0}, {"word": "decent", "count": 33, "sentiment": 0.167}, {"word": "tasty", "count": 29, "sentiment": 0.0}, {"word": "find", "count": 29, "sentiment": 0.0}, {"word": "liked", "count": 27, "sentiment": 0.6}, {"word": "see", "count": 27, "sentiment": 0.0}, {"word": "red", "count": 26, "sentiment": 0.0}, {"word": "tasted", "count": 25, "sentiment": 0.0}, {"word": "looking", "count": 25, "sentiment": 0.0}, {"word": "delicious", "count": 24, "sentiment": 1.0}, {"word": "fine", "count": 24, "sentiment": 0.417}, {"word": "cooked", "count": 24, "sentiment": 0.0}, {"word": "korean", "count": 24, "sentiment": 0.0}, {"word": "eat", "count": 23, "sentiment": 0.0}, {"word": "going", "count": 23, "sentiment": 0.0}, {"word": "served", "count": 23, "sentiment": 0.0}, {"word": "friendly", "count": 22, "sentiment": 0.375}, {"word": "seemed", "count": 22, "sentiment": 0.0}, {"word": "better", "count": 22, "sentiment": 0.5}, {"word": "chinese", "count": 22, "sentiment": 0.0}, {"word": "different", "count": 21, "sentiment": 0.0}, {"word": "sure", "count": 21, "sentiment": 0.5}, {"word": "enjoyed", "count": 21, "sentiment": 0.5}, {"word": "give", "count": 20, "sentiment": 0.0}, {"word": "big", "count": 20, "sentiment": 0.0}, {"word": "expect", "count": 20, "sentiment": 0.0}, {"word": "found", "count": 20, "sentiment": 0.0}, {"word": "special", "count": 20, "sentiment": 0.357}, {"word": "clean", "count": 19, "sentiment": 0.367}, {"word": "busy", "count": 19, "sentiment": 0.1}, {"word": "ask", "count": 18, "sentiment": 0.0}, {"word": "seated", "count": 18, "sentiment": 0.0}, {"word": "solid", "count": 18, "sentiment": 0.0}, {"word": "decided", "count": 17, "sentiment": 0.0}, {"word": "long", "count": 17, "sentiment": -0.05}, {"word": "disappointed", "count": 17, "sentiment": -0.75}, {"word": "makes", "count": 17, "sentiment": 0.0}, {"word": "quick", "count": 17, "sentiment": 0.333}, {"word": "ate", "count": 17, "sentiment": 0.0}], "regular": [{"word": "ordered", "count": 90, "sentiment": 0.0}, {"word": "nice", "count": 53, "sentiment": 0.6}, {"word": "little", "count": 47, "sentiment": -0.188}, {"word": "give", "count": 45, "sentiment": 0.0}, {"word": "better", "count": 40, "sentiment": 0.5}, {"word": "hot", "count": 36, "sentiment": 0.25}, {"word": "sure", "count": 35, "sentiment": 0.5}, {"word": "love", "count": 31, "sentiment": 0.5}, {"word": "going", "count": 30, "sentiment": 0.0}, {"word": "see", "count": 30, "sentiment": 0.0}, {"word": "small", "count": 28, "sentiment": -0.25}, {"word": "fried", "count": 28, "sentiment": 0.0}, {"word": "served", "count": 28, "sentiment": 0.0}, {"word": "left", "count": 28, "sentiment": 0.0}, {"word": "delicious", "count": 28, "sentiment": 1.0}, {"word": "korean", "count": 28, "sentiment": 0.0}, {"word": "many", "count": 26, "sentiment": 0.5}, {"word": "decent", "count": 26, "sentiment": 0.167}, {"word": "find", "count": 25, "sentiment": 0.0}, {"word": "eat", "count": 23, "sentiment": 0.0}, {"word": "used", "count": 23, "sentiment": 0.0}, {"word": "seemed", "count": 23, "sentiment": 0.0}, {"word": "average", "count": 23, "sentiment": -0.15}, {"word": "cooked", "count": 22, "sentiment": 0.0}, {"word": "large", "count": 22, "sentiment": 0.214}, {"word": "big", "count": 22, "sentiment": 0.0}, {"word": "friendly", "count": 22, "sentiment": 0.375}, {"word": "disappointed", "count": 21, "sentiment": -0.75}, {"word": "different", "count": 21, "sentiment": 0.0}, {"word": "long", "count": 20, "sentiment": -0.05}, {"word": "several", "count": 20, "sentiment": 0.0}, {"word": "ask", "count": 20, "sentiment": 0.0}, {"word": "seated", "count": 20, "sentiment": 0.0}, {"word": "getting", "count": 19, "sentiment": 0.0}, {"word": "cheese", "count": 19, "sentiment": 0.0}, {"word": "looked", "count": 19, "sentiment": 0.0}, {"word": "fresh", "count": 19, "sentiment": 0.3}, {"word": "high", "count": 19, "sentiment": 0.16}, {"word": "special", "count": 19, "sentiment": 0.357}, {"word": "tasty", "count": 19, "sentiment": 0.0}, {"word": "decided", "count": 19, "sentiment": 0.0}, {"word": "extra", "count": 19, "sentiment": 0.0}, {"word": "cold", "count": 18, "sentiment": -0.6}, {"word": "looking", "count": 18, "sentiment": 0.0}, {"word": "liked", "count": 18, "sentiment": 0.6}, {"word": "recommend", "count": 18, "sentiment": 0.0}, {"word": "amazing", "count": 18, "sentiment": 0.6}, {"word": "clean", "count": 17, "sentiment": 0.367}, {"word": "least", "count": 17, "sentiment": -0.3}, {"word": "overall", "count": 16, "sentiment": 0.0}]}, "4": {"elite": [{"word": "ordered", "count": 164, "sentiment": 0.0}, {"word": "little", "count": 140, "sentiment": -0.188}, {"word": "nice", "count": 124, "sentiment": 0.6}, {"word": "delicious", "count": 113, "sentiment": 1.0}, {"word": "fried", "count": 105, "sentiment": 0.0}, {"word": "fresh", "count": 98, "sentiment": 0.3}, {"word": "korean", "count": 97, "sentiment": 0.0}, {"word": "hot", "count": 91, "sentiment": 0.25}, {"word": "excellent", "count": 84, "sentiment": 1.0}, {"word": "small", "count": 74, "sentiment": -0.25}, {"word": "sweet", "count": 73, "sentiment": 0.35}, {"word": "cheese", "count": 70, "sentiment": 0.0}, {"word": "friendly", "count": 68, "sentiment": 0.375}, {"word": "tasty", "count": 62, "sentiment": 0.0}, {"word": "love", "count": 59, "sentiment": 0.5}, {"word": "large", "count": 56, "sentiment": 0.214}, {"word": "many", "count": 56, "sentiment": 0.5}, {"word": "eat", "count": 55, "sentiment": 0.0}, {"word": "give", "count": 55, "sentiment": 0.0}, {"word": "different", "count": 52, "sentiment": 0.0}, {"word": "served", "count": 52, "sentiment": 0.0}, {"word": "green", "count": 51, "sentiment": -0.2}, {"word": "enjoyed", "count": 50, "sentiment": 0.5}, {"word": "big", "count": 49, "sentiment": 0.0}, {"word": "sure", "count": 48, "sentiment": 0.5}, {"word": "perfect", "count": 47, "sentiment": 1.0}, {"word": "white", "count": 43, "sentiment": 0.0}, {"word": "huge", "count": 43, "sentiment": 0.4}, {"word": "special", "count": 43, "sentiment": 0.357}, {"word": "liked", "count": 42, "sentiment": 0.6}, {"word": "red", "count": 42, "sentiment": 0.0}, {"word": "going", "count": 41, "sentiment": 0.0}, {"word": "favorite", "count": 41, "sentiment": 0.5}, {"word": "happy", "count": 39, "sentiment": 0.8}, {"word": "clean", "count": 38, "sentiment": 0.367}, {"word": "enjoy", "count": 38, "sentiment": 0.4}, {"word": "full", "count": 38, "sentiment": 0.35}, {"word": "mexican", "count": 38, "sentiment": 0.0}, {"word": "thought", "count": 36, "sentiment": 0.0}, {"word": "tasted", "count": 36, "sentiment": 0.0}, {"word": "olive", "count": 35, "sentiment": 0.0}, {"word": "chicken", "count": 35, "sentiment": -0.6}, {"word": "recommend", "count": 33, "sentiment": 0.0}, {"word": "loved", "count": 33, "sentiment": 0.7}, {"word": "right", "count": 33, "sentiment": 0.286}, {"word": "quick", "count": 32, "sentiment": 0.333}, {"word": "pick", "count": 32, "sentiment": 0.0}, {"word": "italian", "count": 32, "sentiment": 0.0}, {"word": "eating", "count": 31, "sentiment": 0.0}, {"word": "super", "count": 31, "sentiment": 0.333}], "regular": [{"word": "nice", "count": 130, "sentiment": 0.6}, {"word": "delicious", "count": 124, "sentiment": 1.0}, {"word": "little", "count": 122, "sentiment": -0.188}, {"word": "ordered", "count": 114, "sentiment": 0.0}, {"word": "fresh", "count": 91, "sentiment": 0.3}, {"word": "love", "count": 88, "sentiment": 0.5}, {"word": "excellent", "count": 84, "sentiment": 1.0}, {"word": "friendly", "count": 69, "sentiment": 0.375}, {"word": "korean", "count": 65, "sentiment": 0.0}, {"word": "hot", "count": 64, "sentiment": 0.25}, {"word": "tasty", "count": 61, "sentiment": 0.0}, {"word": "going", "count": 53, "sentiment": 0.0}, {"word": "fried", "count": 53, "sentiment": 0.0}, {"word": "give", "count": 50, "sentiment": 0.0}, {"word": "different", "count": 48, "sentiment": 0.0}, {"word": "recommend", "count": 46, "sentiment": 0.0}, {"word": "eat", "count": 46, "sentiment": 0.0}, {"word": "small", "count": 46, "sentiment": -0.25}, {"word": "cheese", "count": 45, "sentiment": 0.0}, {"word": "favorite", "count": 43, "sentiment": 0.5}, {"word": "sure", "count": 43, "sentiment": 0.5}, {"word": "big", "count": 42, "sentiment": 0.0}, {"word": "special", "count": 41, "sentiment": 0.357}, {"word": "awesome", "count": 39, "sentiment": 1.0}, {"word": "find", "count": 39, "sentiment": 0.0}, {"word": "enjoyed", "count": 38, "sentiment": 0.5}, {"word": "amazing", "count": 38, "sentiment": 0.6}, {"word": "overall", "count": 37, "sentiment": 0.0}, {"word": "sweet", "count": 36, "sentiment": 0.35}, {"word": "many", "count": 36, "sentiment": 0.5}, {"word": "chinese", "count": 36, "sentiment": 0.0}, {"word": "looking", "count": 34, "sentiment": 0.0}, {"word": "huge", "count": 34, "sentiment": 0.4}, {"word": "large", "count": 33, "sentiment": 0.214}, {"word": "happy", "count": 32, "sentiment": 0.8}, {"word": "cooked", "count": 31, "sentiment": 0.0}, {"word": "loved", "count": 31, "sentiment": 0.7}, {"word": "better", "count": 30, "sentiment": 0.5}, {"word": "quick", "count": 30, "sentiment": 0.333}, {"word": "decent", "count": 29, "sentiment": 0.167}, {"word": "italian", "count": 29, "sentiment": 0.0}, {"word": "found", "count": 29, "sentiment": 0.0}, {"word": "enjoy", "count": 28, "sentiment": 0.4}, {"word": "perfect", "count": 28, "sentiment": 1.0}, {"word": "old", "count": 28, "sentiment": 0.1}, {"word": "french", "count": 27, "sentiment": 0.0}, {"word": "served", "count": 27, "sentiment": 0.0}, {"word": "full", "count": 25, "sentiment": 0.35}, {"word": "super", "count": 25, "sentiment": 0.333}, {"word": "chicken", "count": 25, "sentiment": -0.6}]}, "5": {"elite": [{"word": "delicious", "count": 188, "sentiment": 1.0}, {"word": "ordered", "count": 128, "sentiment": 0.0}, {"word": "love", "count": 104, "sentiment": 0.5}, {"word": "little", "count": 92, "sentiment": -0.188}, {"word": "fresh", "count": 91, "sentiment": 0.3}, {"word": "nice", "count": 87, "sentiment": 0.6}, {"word": "amazing", "count": 87, "sentiment": 0.6}, {"word": "excellent", "count": 82, "sentiment": 1.0}, {"word": "friendly", "count": 81, "sentiment": 0.375}, {"word": "korean", "count": 70, "sentiment": 0.0}, {"word": "favorite", "count": 67, "sentiment": 0.5}, {"word": "sweet", "count": 65, "sentiment": 0.35}, {"word": "hot", "count": 64, "sentiment": 0.25}, {"word": "super", "count": 59, "sentiment": 0.333}, {"word": "full", "count": 58, "sentiment": 0.35}, {"word": "eat", "count": 58, "sentiment": 0.0}, {"word": "small", "count": 58, "sentiment": -0.25}, {"word": "loved", "count": 57, "sentiment": 0.7}, {"word": "perfect", "count": 56, "sentiment": 1.0}, {"word": "fantastic", "count": 54, "sentiment": 0.4}, {"word": "fried", "count": 54, "sentiment": 0.0}, {"word": "recommend", "count": 54, "sentiment": 0.0}, {"word": "served", "count": 52, "sentiment": 0.0}, {"word": "cooked", "count": 51, "sentiment": 0.0}, {"word": "tasty", "count": 48, "sentiment": 0.0}, {"word": "large", "count": 48, "sentiment": 0.214}, {"word": "different", "count": 48, "sentiment": 0.0}, {"word": "see", "count": 47, "sentiment": 0.0}, {"word": "many", "count": 47, "sentiment": 0.5}, {"word": "happy", "count": 46, "sentiment": 0.8}, {"word": "awesome", "count": 45, "sentiment": 1.0}, {"word": "big", "count": 45, "sentiment": 0.0}, {"word": "special", "count": 45, "sentiment": 0.357}, {"word": "sure", "count": 43, "sentiment": 0.5}, {"word": "extra", "count": 43, "sentiment": 0.0}, {"word": "red", "count": 41, "sentiment": 0.0}, {"word": "cheese", "count": 40, "sentiment": 0.0}, {"word": "flavorful", "count": 37, "sentiment": 0.0}, {"word": "going", "count": 36, "sentiment": 0.0}, {"word": "found", "count": 36, "sentiment": 0.0}, {"word": "top", "count": 35, "sentiment": 0.5}, {"word": "ate", "count": 35, "sentiment": 0.0}, {"word": "clean", "count": 35, "sentiment": 0.367}, {"word": "find", "count": 35, "sentiment": 0.0}, {"word": "free", "count": 34, "sentiment": 0.4}, {"word": "white", "count": 34, "sentiment": 0.0}, {"word": "italian", "count": 33, "sentiment": 0.0}, {"word": "better", "count": 33, "sentiment": 0.5}, {"word": "thai", "count": 33, "sentiment": 0.0}, {"word": "fast", "count": 32, "sentiment": 0.2}], "regular": [{"word": "delicious", "count": 454, "sentiment": 1.0}, {"word": "love", "count": 333, "sentiment": 0.5}, {"word": "amazing", "count": 313, "sentiment": 0.6}, {"word": "friendly", "count": 278, "sentiment": 0.375}, {"word": "fresh", "count": 235, "sentiment": 0.3}, {"word": "nice", "count": 214, "sentiment": 0.6}, {"word": "ordered", "count": 212, "sentiment": 0.0}, {"word": "recommend", "count": 201, "sentiment": 0.0}, {"word": "favorite", "count": 183, "sentiment": 0.5}, {"word": "excellent", "count": 178, "sentiment": 1.0}, {"word": "hot", "count": 174, "sentiment": 0.25}, {"word": "awesome", "count": 136, "sentiment": 1.0}, {"word": "wonderful", "count": 133, "sentiment": 1.0}, {"word": "eat", "count": 120, "sentiment": 0.0}, {"word": "perfect", "count": 120, "sentiment": 1.0}, {"word": "going", "count": 115, "sentiment": 0.0}, {"word": "little", "count": 114, "sentiment": -0.188}, {"word": "korean", "count": 114, "sentiment": 0.0}, {"word": "fantastic", "count": 112, "sentiment": 0.4}, {"word": "fried", "count": 108, "sentiment": 0.0}, {"word": "many", "count": 106, "sentiment": 0.5}, {"word": "happy", "count": 93, "sentiment": 0.8}, {"word": "loved", "count": 92, "sentiment": 0.7}, {"word": "italian", "count": 92, "sentiment": 0.0}, {"word": "looking", "count": 91, "sentiment": 0.0}, {"word": "special", "count": 91, "sentiment": 0.357}, {"word": "sweet", "count": 91, "sentiment": 0.35}, {"word": "cheese", "count": 89, "sentiment": 0.0}, {"word": "sure", "count": 85, "sentiment": 0.5}, {"word": "super", "count": 84, "sentiment": 0.333}, {"word": "huge", "count": 84, "sentiment": 0.4}, {"word": "small", "count": 81, "sentiment": -0.25}, {"word": "full", "count": 81, "sentiment": 0.35}, {"word": "attentive", "count": 80, "sentiment": 0.4}, {"word": "chinese", "count": 76, "sentiment": 0.0}, {"word": "better", "count": 75, "sentiment": 0.5}, {"word": "tasty", "count": 75, "sentiment": 0.0}, {"word": "different", "count": 75, "sentiment": 0.0}, {"word": "enjoyed", "count": 74, "sentiment": 0.5}, {"word": "big", "count": 73, "sentiment": 0.0}, {"word": "clean", "count": 73, "sentiment": 0.367}, {"word": "find", "count": 72, "sentiment": 0.0}, {"word": "served", "count": 68, "sentiment": 0.0}, {"word": "coming", "count": 68, "sentiment": 0.0}, {"word": "give", "count": 67, "sentiment": 0.0}, {"word": "top", "count": 66, "sentiment": 0.5}, {"word": "see", "count": 65, "sentiment": 0.0}, {"word": "disappointed", "count": 64, "sentiment": -0.75}, {"word": "found", "count": 64, "sentiment": 0.0}, {"word": "authentic", "count": 60, "sentiment": 0.5}]}}}